Workbook

Sheet 00_Summary
B2: Liguria Hospitality Agentic Hardware — Investment Pack
B3: RU / IT / EN | Версия 1.0 | Все суммы EUR без IVA; финансовые входные данные являются сценарными допущениями, не котировками поставщиков.
B5: Решение / Soluzione / Solution
B6: Тема | C6: Русский | D6: Italiano | E6: English
B7: Рекомендация | C7: Начать с Hotel Agent OS + lobby GuestNode + Smart Travel Wall/locker; IoT Energy — второй модуль. | D7: Partire da Hotel Agent OS + GuestNode lobby + Smart Travel Wall/locker; IoT Energy come secondo modulo. | E7: Start with Hotel Agent OS + lobby GuestNode + Smart Travel Wall/locker; add IoT Energy second.
B8: Почему Лигурия | C8: В 2025 г.: 6,267,091 arrivals и 20,702,403 presences с AAUT; иностранный поток 3,218,375 arrivals. | D8: Nel 2025: 6.267.091 arrivi e 20.702.403 presenze incl. AAUT; 3.218.375 arrivi esteri. | E8: In 2025: 6,267,091 arrivals and 20,702,403 presences incl. AAUT; 3,218,375 foreign arrivals.
B9: Инвестиционная логика | C9: Hardware — wedge и retention; recurring margin должен идти из SaaS, service и transactions. | D9: L’hardware è wedge e retention; il margine ricorrente deve venire da SaaS, servizi e transazioni. | E9: Hardware is the wedge and retention anchor; recurring margin must come from SaaS, services and transactions.
B10: Не запускать сначала | C10: Роботы и vape vending: высокий CAPEX/регуляторная неопределённость. | D10: Non avviare per primi robot e vape vending: CAPEX/rischio normativo elevati. | E10: Do not lead with robots or vape vending: high CAPEX/regulatory risk.
B13: Ключевые выводы модели / Conclusioni / Key model outputs
B14: Метрика | C14: Формула | D14: Комментарий
B15: Base: cash funding need | C15: ="€ "&TEXT(MAX(0,-MIN('06_Cashflow'!B31:Y31)),"#,##0") | D15: Сценарий Base, 24 месяца / Scenario Base, 24 mesi / Base scenario, 24 months
B16: Year 1 revenue | C16: ="€ "&TEXT('05_P&L'!C21,"#,##0") | D16: Выручка / Ricavi / Revenue
B17: Year 2 revenue | C17: ="€ "&TEXT('05_P&L'!D21,"#,##0") | D17: Выручка / Ricavi / Revenue
B18: Year 2 EBITDA | C18: ="€ "&TEXT('05_P&L'!D34,"#,##0") | D18: До амортизации; pre-ammortamenti; pre-depreciation
B19: Month EBITDA positive | C19: =MATCH(TRUE,'05_P&L'!C34:Z34>0,0) | D19: Месяц в модели / mese nel modello / month in model
B22: Источник рынка: Regione Liguria, Turismo in Liguria — anno 2025; Istat capacity data are published at municipal level. Regulatory sources: European Commission CRA/RED, Garante Privacy.

Sheet 01_Assumptions
B2: Допущения / Assunzioni / Assumptions
B3: Жёлтые ячейки — изменяемые входные данные. Синие цифры — hardcoded scenario assumptions, не vendor quotes.
B5: Группа / Gruppo / Group | C5: Параметр / Parametro / Parameter | D5: Base | E5: Ед. / U.M. / Unit | F5: Комментарий / Comment
B6: Operating model | C6: Pilot hotels Y1 | D6: 12 | E6: properties | F6: Base scenario
B7: Operating model | C7: Hotels at end Y2 | D7: 45 | E7: properties | F7: Base scenario
B8: Operating model | C8: Average rooms/property | D8: 35 | E8: rooms | F8: Target ICP 20–80 rooms
B9: Pricing | C9: Agent OS setup fee | D9: 1800 | E9: EUR/property | F9: Scenario assumption
B10: Pricing | C10: Agent OS monthly | D10: 390 | E10: EUR/property/month | F10: Scenario assumption
B11: Pricing | C11: GuestNode monthly | D11: 95 | E11: EUR/device/month | F11: Scenario assumption
B12: Pricing | C12: Travel Wall monthly | D12: 180 | E12: EUR/property/month | F12: Scenario assumption
B13: Pricing | C13: IoT Energy monthly | D13: 4.5 | E13: EUR/room/month | F13: Scenario assumption
B14: Hardware deployed | C14: GuestNode landed + install | D14: 620 | E14: EUR/device | F14: Scenario assumption
B15: Hardware deployed | C15: Travel Wall landed + install | D15: 4200 | E15: EUR/unit | F15: Scenario assumption
B16: Hardware deployed | C16: IoT Energy kit/room landed+install | D16: 155 | E16: EUR/room | F16: Scenario assumption
B17: Unit economics | C17: Transaction gross margin/property/month | D17: 110 | E17: EUR/property/month | F17: Scenario assumption
... B25: Fixed OPEX | C25: Monthly OPEX growth Y2 | D25: 0.18 | E25: % | F25: Scenario assumption

Sheet 02_Categories
B2: Категории / Categorie / Categories
B3: Рейтинг: 1 = запускать; 5 = не запускать в первом цикле. CAPEX приведён как модельное допущение.
B5: Категория | C5: Формат | D5: Доход | E5: CAPEX риск | F5: Regulatory риск | G5: Приоритет | H5: Стартовая оценка | I5: Долговечность | J5: Решение
B6: Hotel Agent OS | C6: SaaS/FDE | D6: Setup + monthly SaaS | E6: Low | F6: High | G6: 1 | H6: € 1,800 setup; €390/mo | I6: Long | J6: Core
B7: Lobby GuestNode | C7: tablet/voice endpoint | D7: Lease + SaaS | E7: Medium | F7: Medium | G7: 1 | H7: €620 deployed | I7: Medium | J7: Pilot 1/property
B8: Smart Travel Wall | C8: vending/locker | D8: SaaS + retail/commission | E8: Medium | F8: Medium | G8: 1 | H8: €4,200 deployed | I8: Long | J8: Use essentials/rentals
B9: IoT Energy Kit | C9: sensors/controls | D9: SaaS + hardware | E9: Medium | F9: Medium | G9: 1 | H9: €155/room | I9: Very long | J9: Measured saving required
B10: Rental/Luggage Lockers | C10: lockers | D10: Rental + SaaS | E10: Medium | F10: Low | G10: 2 | H10: €3,500–€6,000 deployed | I10: Long | J10: Tourist clusters
B11: Smart Access | C11: locks/access | D11: Hardware + SaaS | E11: Medium | F11: High | G11: 2 | H11: Case-by-case | I11: Very long | J11: Partner locksmith
B12: Check-in/ID Kiosk | C12: kiosk/scanner | D12: Lease + setup | E12: High | F12: High | G12: 3 | H12: €6,000–€12,000 | I12: Medium | J12: Compliance-first
B13: Cleaning robot | C13: robot | D13: Lease/service | E13: High | F13: Medium | G13: 3 | H13: €12,000–€25,000 | I13: Medium | J13: Only high-volume
B14: Delivery robot | C14: robot | D14: Lease/service | E14: High | F14: Medium | G14: 4 | H14: €18,000–€35,000 | I14: Medium | J14: API first, buy later
B15: Vape vending | C15: regulated vending | D15: Margin/operator fee | E15: Medium | F15: Very high | G15: 5 | H15: Legal-led | I15: Uncertain | J15: Licensed operator only

Sheet 03_Licences
B2: Лицензии и compliance / Licenze e compliance / Licences & compliance
B3: Это рабочая карта, не юридическое заключение. До запуска нужна проверка итальянским avvocato/commercialista.
B5: Категория | C5: Требование | D5: Норма/орган | E5: Практическая мера | F5: Статус
B6: Agentic SaaS | C6: GDPR, DPA, security, records of processing | D6: GDPR; contracts | E6: EU hosting, data minimisation, audit logs | F6: Must-have
B7: Guest ID / check-in | C7: Alloggiati Web; identity data handling | D7: TULPS Art. 109 / Police workflow | E7: Send required data; erase document copies after reporting | F7: Must-have
B8: Wi-Fi/BLE/Zigbee device | C8: CE, RED, EMC, RoHS, DoC, technical file | D8: EU product rules | E8: Verify pre-shipment; retain documentation | F8: Must-have
B9: Connected IoT | C9: CRA vulnerability/security lifecycle | D9: CRA / RED cyber provisions | E9: SBOM, OTA updates, vendor support commitment | F9: Must-have
B10: Payment | C10: PSP/acquirer; PCI handled by provider | D10: Payments | E10: Use certified terminal; do not store card data | F10: Must-have
B11: Food/retail vending | C11: Local SUAP/SCIA, food labelling/HACCP as applicable | D11: Municipal/health rules | E11: Use licensed local operator initially | F11: Before sale
B12: Alcohol vending | C12: Age/local licensing rules | D12: Local rules | E12: Legal review per municipality | F12: Defer
B13: Vapes/tobacco | C13: ADM authorisation, age checks, advertising rules | D13: ADM / tobacco rules | E13: Licensed operator partnership only | F13: Do not direct-sell
B14: Smart locks | C14: Product conformity, fire/egress compatibility | D14: EU + building/fire requirements | E14: Use certified products & locksmith | F14: Before installation
B15: Robots | C15: CE/product safety, insurance, site risk assessment | D15: EU product safety | E15: Supervised pilot, liability cover | F15: Before deployment
B18: Ключевые факты: Garante Privacy запрещает хранить копии документов после времени, необходимого для передачи в Alloggiati Web; CRA полностью применяется с 11.12.2027, reporting obligations — с 11.09.2026.

Sheet 04_Deploy
B2: Развёртывание / Deployment
B3: Base case monthly deployments drive P&L and cash flow.
B5: Month | C5: New hotels | D5: Cumulative hotels | E5: GuestNodes deployed | F5: Travel Walls deployed | G5: IoT rooms deployed | H5: Setup revenue EUR | I5: Hardware CAPEX EUR
B6: 1 | C6: 1 | D6: =SUM($C$6:C6) | E6: =C6 | F6: =C6 | G6: =C6*'01_Assumptions'!$D$8 | H6: =C6*'01_Assumptions'!$D$5*0+'01_Assumptions'!$D$14*C6+'01_Assumptions'!$D$15*C6+'01_Assumptions'!$D$16*C6*'01_Assumptions'!$D$7 | I6: =D6*'01_Assumptions'!$D$8
B7: 2 | C7: 1 | D7: =SUM($C$6:C7) | E7: =C7 | F7: =C7 | G7: =C7*'01_Assumptions'!$D$8 | H7: =C7*'01_Assumptions'!$D$5*0+'01_Assumptions'!$D$14*C7+'01_Assumptions'!$D$15*C7+'01_Assumptions'!$D$16*C7*'01_Assumptions'!$D$7 | I7: =D7*'01_Assumptions'!$D$8
B8: 3 | C8: 1 | D8: =SUM($C$6:C8) | E8: =C8 | F8: =C8 | G8: =C8*'01_Assumptions'!$D$8 | H8: =C8*'01_Assumptions'!$D$5*0+'01_Assumptions'!$D$14*C8+'01_Assumptions'!$D$15*C8+'01_Assumptions'!$D$16*C8*'01_Assumptions'!$D$7 | I8: =D8*'01_Assumptions'!$D$8
B9: 4 | C9: 1 | D9: =SUM($C$6:C9) | E9: =C9 | F9: =C9 | G9: =C9*'01_Assumptions'!$D$8 | H9: =C9*'01_Assumptions'!$D$5*0+'01_Assumptions'!$D$14*C9+'01_Assumptions'!$D$15*C9+'01_Assumptions'!$D$16*C9*'01_Assumptions'!$D$7 | I9: =D9*'01_Assumptions'!$D$8
B10: 5 | C10: 1 | D10: =SUM($C$6:C10) | E10: =C10 | F10: =C10 | G10: =C10*'01_Assumptions'!$D$8 | H10: =C10*'01_Assumptions'!$D$5*0+'01_Assumptions'!$D$14*C10+'01_Assumptions'!$D$15*C10+'01_Assumptions'!$D$16*C10*'01_Assumptions'!$D$7 | I10: =D10*'01_Assumptions'!$D$8
B11: 6 | C11: 1 | D11: =SUM($C$6:C11) | E11: =C11 | F11: =C11 | G11: =C11*'01_Assumptions'!$D$8 | H11: =C11*'01_Assumptions'!$D$5*0+'01_Assumptions'!$D$14*C11+'01_Assumptions'!$D$15*C11+'01_Assumptions'!$D$16*C11*'01_Assumptions'!$D$7 | I11: =D11*'01_Assumptions'!$D$8
B12: 7 | C12: 2 | D12: =SUM($C$6:C12) | E12: =C12 | F12: =C12 | G12: =C12*'01_Assumptions'!$D$8 | H12: =C12*'01_Assumptions'!$D$5*0+'01_Assumptions'!$D$14*C12+'01_Assumptions'!$D$15*C12+'01_Assumptions'!$D$16*C12*'01_Assumptions'!$D$7 | I12: =D12*'01_Assumptions'!$D$8
B13: 8 | C13: 2 | D13: =SUM($C$6:C13) | E13: =C13 | F13: =C13 | G13: =C13*'01_Assumptions'!$D$8 | H13: =C13*'01_Assumptions'!$D$5*0+'01_Assumptions'!$D$14*C13+'01_Assumptions'!$D$15*C13+'01_Assumptions'!$D$16*C13*'01_Assumptions'!$D$7 | I13: =D13*'01_Assumptions'!$D$8
B14: 9 | C14: 2 | D14: =SUM($C$6:C14) | E14: =C14 | F14: =C14 | G14: =C14*'01_Assumptions'!$D$8 | H14: =C14*'01_Assumptions'!$D$5*0+'01_Assumptions'!$D$14*C14+'01_Assumptions'!$D$15*C14+'01_Assumptions'!$D$16*C14*'01_Assumptions'!$D$7 | I14: =D14*'01_Assumptions'!$D$8
B15: 10 | C15: 2 | D15: =SUM($C$6:C15) | E15: =C15 | F15: =C15 | G15: =C15*'01_Assumptions'!$D$8 | H15: =C15*'01_Assumptions'!$D$5*0+'01_Assumptions'!$D$14*C15+'01_Assumptions'!$D$15*C15+'01_Assumptions'!$D$16*C15*'01_Assumptions'!$D$7 | I15: =D15*'01_Assumptions'!$D$8
B16: 11 | C16: 2 | D16: =SUM($C$6:C16) | E16: =C16 | F16: =C16 | G16: =C16*'01_Assumptions'!$D$8 | H16: =C16*'01_Assumptions'!$D$5*0+'01_Assumptions'!$D$14*C16+'01_Assumptions'!$D$15*C16+'01_Assumptions'!$D$16*C16*'01_Assumptions'!$D$7 | I16: =D16*'01_Assumptions'!$D$8
B17: 12 | C17: 2 | D17: =SUM($C$6:C17) | E17: =C17 | F17: =C17 | G17: =C17*'01_Assumptions'!$D$8 | H17: =C17*'01_Assumptions'!$D$5*0+'01_Assumptions'!$D$14*C17+'01_Assumptions'!$D$15*C17+'01_Assumptions'!$D$16*C17*'01_Assumptions'!$D$7 | I17: =D17*'01_Assumptions'!$D$8
... B29: 24 | C29: 3 | D29: =SUM($C$6:C29) | E29: =C29 | F29: =C29 | G29: =C29*'01_Assumptions'!$D$8 | H29: =C29*'01_Assumptions'!$D$5*0+'01_Assumptions'!$D$14*C29+'01_Assumptions'!$D$15*C29+'01_Assumptions'!$D$16*C29*'01_Assumptions'!$D$7 | I29: =D29*'01_Assumptions'!$D$8

Sheet 05_P&L
B2: P&L / Conto economico / Profit & Loss
B3: 24-month Base scenario. Formulas link to assumptions and deployment.
B5: Line item | C5: M1 | D5: M2 | E5: M3 | F5: M4 | G5: M5 | H5: M6 | I5: M7 | J5: M8 | K5: M9 | L5: M10 | M5: M11 | N5: M12 | O5: M13 | P5: M14 | Q5: M15 | R5: M16 | S5: M17 | T5: M18 | U5: M19 | V5: M20 | W5: M21 | X5: M22 | Y5: M23 | Z5: M24 | AA5: Y1 | AB5: Y2
B6: Hotels active | C6: ='04_Deploy'!D6 | D6: ='04_Deploy'!D7 | E6: ='04_Deploy'!D8 | F6: ='04_Deploy'!D9 | G6: ='04_Deploy'!D10 | H6: ='04_Deploy'!D11 | I6: ='04_Deploy'!D12 | J6: ='04_Deploy'!D13 | K6: ='04_Deploy'!D14 | L6: ='04_Deploy'!D15 | M6: ='04_Deploy'!D16 | N6: ='04_Deploy'!D17 | O6: ='04_Deploy'!D18 | P6: ='04_Deploy'!D19 | Q6: ='04_Deploy'!D20 | R6: ='04_Deploy'!D21 | S6: ='04_Deploy'!D22 | T6: ='04_Deploy'!D23 | U6: ='04_Deploy'!D24 | V6: ='04_Deploy'!D25 | W6: ='04_Deploy'!D26 | X6: ='04_Deploy'!D27 | Y6: ='04_Deploy'!D28 | Z6: ='04_Deploy'!D29 | AA6: =SUM(C6:N6) | AB6: =SUM(O6:Z6)
B7: Setup fees | C7: ='04_Deploy'!C6*'01_Assumptions'!$D$9 | D7: ='04_Deploy'!C7*'01_Assumptions'!$D$9 | E7: ='04_Deploy'!C8*'01_Assumptions'!$D$9 | F7: ='04_Deploy'!C9*'01_Assumptions'!$D$9 | G7: ='04_Deploy'!C10*'01_Assumptions'!$D$9 | H7: ='04_Deploy'!C11*'01_Assumptions'!$D$9 | I7: ='04_Deploy'!C12*'01_Assumptions'!$D$9 | J7: ='04_Deploy'!C13*'01_Assumptions'!$D$9 | K7: ='04_Deploy'!C14*'01_Assumptions'!$D$9 | L7: ='04_Deploy'!C15*'01_Assumptions'!$D$9 | M7: ='04_Deploy'!C16*'01_Assumptions'!$D$9 | N7: ='04_Deploy'!C17*'01_Assumptions'!$D$9 | O7: ='04_Deploy'!C18*'01_Assumptions'!$D$9 | P7: ='04_Deploy'!C19*'01_Assumptions'!$D$9 | Q7: ='04_Deploy'!C20*'01_Assumptions'!$D$9 | R7: ='04_Deploy'!C21*'01_Assumptions'!$D$9 | S7: ='04_Deploy'!C22*'01_Assumptions'!$D$9 | T7: ='04_Deploy'!C23*'01_Assumptions'!$D$9 | U7: ='04_Deploy'!C24*'01_Assumptions'!$D$9 | V7: ='04_Deploy'!C25*'01_Assumptions'!$D$9 | W7: ='04_Deploy'!C26*'01_Assumptions'!$D$9 | X7: ='04_Deploy'!C27*'01_Assumptions'!$D$9 | Y7: ='04_Deploy'!C28*'01_Assumptions'!$D$9 | Z7: ='04_Deploy'!C29*'01_Assumptions'!$D$9 | AA7: =SUM(C7:N7) | AB7: =SUM(O7:Z7)
B8: Agent OS SaaS | C8: ='04_Deploy'!D6*'01_Assumptions'!$D$10 | D8: ='04_Deploy'!D7*'01_Assumptions'!$D$10 | E8: ='04_Deploy'!D8*'01_Assumptions'!$D$10 | F8: ='04_Deploy'!D9*'01_Assumptions'!$D$10 | G8: ='04_Deploy'!D10*'01_Assumptions'!$D$10 | H8: ='04_Deploy'!D11*'01_Assumptions'!$D$10 | I8: ='04_Deploy'!D12*'01_Assumptions'!$D$10 | J8: ='04_Deploy'!D13*'01_Assumptions'!$D$10 | K8: ='04_Deploy'!D14*'01_Assumptions'!$D$10 | L8: ='04_Deploy'!D15*'01_Assumptions'!$D$10 | M8: ='04_Deploy'!D16*'01_Assumptions'!$D$10 | N8: ='04_Deploy'!D17*'01_Assumptions'!$D$10 | O8: ='04_Deploy'!D18*'01_Assumptions'!$D$10 | P8: ='04_Deploy'!D19*'01_Assumptions'!$D$10 | Q8: ='04_Deploy'!D20*'01_Assumptions'!$D$10 | R8: ='04_Deploy'!D21*'01_Assumptions'!$D$10 | S8: ='04_Deploy'!D22*'01_Assumptions'!$D$10 | T8: ='04_Deploy'!D23*'01_Assumptions'!$D$10 | U8: ='04_Deploy'!D24*'01_Assumptions'!$D$10 | V8: ='04_Deploy'!D25*'01_Assumptions'!$D$10 | W8: ='04_Deploy'!D26*'01_Assumptions'!$D$10 | X8: ='04_Deploy'!D27*'01_Assumptions'!$D$10 | Y8: ='04_Deploy'!D28*'01_Assumptions'!$D$10 | Z8: ='04_Deploy'!D29*'01_Assumptions'!$D$10 | AA8: =SUM(C8:N8) | AB8: =SUM(O8:Z8)
B9: GuestNode SaaS | C9: ='04_Deploy'!D6*'01_Assumptions'!$D$11 | D9: ='04_Deploy'!D7*'01_Assumptions'!$D$11 | E9: ='04_Deploy'!D8*'01_Assumptions'!$D$11 | F9: ='04_Deploy'!D9*'01_Assumptions'!$D$11 | G9: ='04_Deploy'!D10*'01_Assumptions'!$D$11 | H9: ='04_Deploy'!D11*'01_Assumptions'!$D$11 | I9: ='04_Deploy'!D12*'01_Assumptions'!$D$11 | J9: ='04_Deploy'!D13*'01_Assumptions'!$D$11 | K9: ='04_Deploy'!D14*'01_Assumptions'!$D$11 | L9: ='04_Deploy'!D15*'01_Assumptions'!$D$11 | M9: ='04_Deploy'!D16*'01_Assumptions'!$D$11 | N9: ='04_Deploy'!D17*'01_Assumptions'!$D$11 | O9: ='04_Deploy'!D18*'01_Assumptions'!$D$11 | P9: ='04_Deploy'!D19*'01_Assumptions'!$D$11 | Q9: ='04_Deploy'!D20*'01_Assumptions'!$D$11 | R9: ='04_Deploy'!D21*'01_Assumptions'!$D$11 | S9: ='04_Deploy'!D22*'01_Assumptions'!$D$11 | T9: ='04_Deploy'!D23*'01_Assumptions'!$D$11 | U9: ='04_Deploy'!D24*'01_Assumptions'!$D$11 | V9: ='04_Deploy'!D25*'01_Assumptions'!$D$11 | W9: ='04_Deploy'!D26*'01_Assumptions'!$D$11 | X9: ='04_Deploy'!D27*'01_Assumptions'!$D$11 | Y9: ='04_Deploy'!D28*'01_Assumptions'!$D$11 | Z9: ='04_Deploy'!D29*'01_Assumptions'!$D$11 | AA9: =SUM(C9:N9) | AB9: =SUM(O9:Z9)
B10: Travel Wall SaaS | C10: ='04_Deploy'!D6*'01_Assumptions'!$D$12 | D10: ='04_Deploy'!D7*'01_Assumptions'!$D$12 | E10: ='04_Deploy'!D8*'01_Assumptions'!$D$12 | F10: ='04_Deploy'!D9*'01_Assumptions'!$D$12 | G10: ='04_Deploy'!D10*'01_Assumptions'!$D$12 | H10: ='04_Deploy'!D11*'01_Assumptions'!$D$12 | I10: ='04_Deploy'!D12*'01_Assumptions'!$D$12 | J10: ='04_Deploy'!D13*'01_Assumptions'!$D$12 | K10: ='04_Deploy'!D14*'01_Assumptions'!$D$12 | L10: ='04_Deploy'!D15*'01_Assumptions'!$D$12 | M10: ='04_Deploy'!D16*'01_Assumptions'!$D$12 | N10: ='04_Deploy'!D17*'01_Assumptions'!$D$12 | O10: ='04_Deploy'!D18*'01_Assumptions'!$D$12 | P10: ='04_Deploy'!D19*'01_Assumptions'!$D$12 | Q10: ='04_Deploy'!D20*'01_Assumptions'!$D$12 | R10: ='04_Deploy'!D21*'01_Assumptions'!$D$12 | S10: ='04_Deploy'!D22*'01_Assumptions'!$D$12 | T10: ='04_Deploy'!D23*'01_Assumptions'!$D$12 | U10: ='04_Deploy'!D24*'01_Assumptions'!$D$12 | V10: ='04_Deploy'!D25*'01_Assumptions'!$D$12 | W10: ='04_Deploy'!D26*'01_Assumptions'!$D$12 | X10: ='04_Deploy'!D27*'01_Assumptions'!$D$12 | Y10: ='04_Deploy'!D28*'01_Assumptions'!$D$12 | Z10: ='04_Deploy'!D29*'01_Assumptions'!$D$12 | AA10: =SUM(C10:N10) | AB10: =SUM(O10:Z10)
B11: IoT Energy SaaS | C11: ='04_Deploy'!D6*'01_Assumptions'!$D$7*'01_Assumptions'!$D$13 | D11: ='04_Deploy'!D7*'01_Assumptions'!$D$7*'01_Assumptions'!$D$13 | E11: ='04_Deploy'!D8*'01_Assumptions'!$D$7*'01_Assumptions'!$D$13 | F11: ='04_Deploy'!D9*'01_Assumptions'!$D$7*'01_Assumptions'!$D$13 | G11: ='04_Deploy'!D10*'01_Assumptions'!$D$7*'01_Assumptions'!$D$13 | H11: ='04_Deploy'!D11*'01_Assumptions'!$D$7*'01_Assumptions'!$D$13 | I11: ='04_Deploy'!D12*'01_Assumptions'!$D$7*'01_Assumptions'!$D$13 | J11: ='04_Deploy'!D13*'01_Assumptions'!$D$7*'01_Assumptions'!$D$13 | K11: ='04_Deploy'!D14*'01_Assumptions'!$D$7*'01_Assumptions'!$D$13 | L11: ='04_Deploy'!D15*'01_Assumptions'!$D$7*'01_Assumptions'!$D$13 | M11: ='04_Deploy'!D16*'01_Assumptions'!$D$7*'01_Assumptions'!$D$13 | N11: ='04_Deploy'!D17*'01_Assumptions'!$D$7*'01_Assumptions'!$D$13 | O11: ='04_Deploy'!D18*'01_Assumptions'!$D$7*'01_Assumptions'!$D$13 | P11: ='04_Deploy'!D19*'01_Assumptions'!$D$7*'01_Assumptions'!$D$13 | Q11: ='04_Deploy'!D20*'01_Assumptions'!$D$7*'01_Assumptions'!$D$13 | R11: ='04_Deploy'!D21*'01_Assumptions'!$D$7*'01_Assumptions'!$D$13 | S11: ='04_Deploy'!D22*'01_Assumptions'!$D$7*'01_Assumptions'!$D$13 | T11: ='04_Deploy'!D23*'01_Assumptions'!$D$7*'01_Assumptions'!$D$13 | U11: ='04_Deploy'!D24*'01_Assumptions'!$D$7*'01_Assumptions'!$D$13 | V11: ='04_Deploy'!D25*'01_Assumptions'!$D$7*'01_Assumptions'!$D$13 | W11: ='04_Deploy'!D26*'01_Assumptions'!$D$7*'01_Assumptions'!$D$13 | X11: ='04_Deploy'!D27*'01_Assumptions'!$D$7*'01_Assumptions'!$D$13 | Y11: ='04_Deploy'!D28*'01_Assumptions'!$D$7*'01_Assumptions'!$D$13 | Z11: ='04_Deploy'!D29*'01_Assumptions'!$D$7*'01_Assumptions'!$D$13 | AA11: =SUM(C11:N11) | AB11: =SUM(O11:Z11)
B12: Transaction gross margin | C12: ='04_Deploy'!D6*'01_Assumptions'!$D$14 | D12: ='04_Deploy'!D7*'01_Assumptions'!$D$14 | E12: ='04_Deploy'!D8*'01_Assumptions'!$D$14 | F12: ='04_Deploy'!D9*'01_Assumptions'!$D$14 | G12: ='04_Deploy'!D10*'01_Assumptions'!$D$14 | H12: ='04_Deploy'!D11*'01_Assumptions'!$D$14 | I12: ='04_Deploy'!D12*'01_Assumptions'!$D$14 | J12: ='04_Deploy'!D13*'01_Assumptions'!$D$14 | K12: ='04_Deploy'!D14*'01_Assumptions'!$D$14 | L12: ='04_Deploy'!D15*'01_Assumptions'!$D$14 | M12: ='04_Deploy'!D16*'01_Assumptions'!$D$14 | N12: ='04_Deploy'!D17*'01_Assumptions'!$D$14 | O12: ='04_Deploy'!D18*'01_Assumptions'!$D$14 | P12: ='04_Deploy'!D19*'01_Assumptions'!$D$14 | Q12: ='04_Deploy'!D20*'01_Assumptions'!$D$14 | R12: ='04_Deploy'!D21*'01_Assumptions'!$D$14 | S12: ='04_Deploy'!D22*'01_Assumptions'!$D$14 | T12: ='04_Deploy'!D23*'01_Assumptions'!$D$14 | U12: ='04_Deploy'!D24*'01_Assumptions'!$D$14 | V12: ='04_Deploy'!D25*'01_Assumptions'!$D$14 | W12: ='04_Deploy'!D26*'01_Assumptions'!$D$14 | X12: ='04_Deploy'!D27*'01_Assumptions'!$D$14 | Y12: ='04_Deploy'!D28*'01_Assumptions'!$D$14 | Z12: ='04_Deploy'!D29*'01_Assumptions'!$D$14 | AA12: =SUM(C12:N12) | AB12: =SUM(O12:Z12)
B13: Total revenue | C13: =SUM(C7:C12) | D13: =SUM(D7:D12) | E13: =SUM(E7:E12) | F13: =SUM(F7:F12) | G13: =SUM(G7:G12) | H13: =SUM(H7:H12) | I13: =SUM(I7:I12) | J13: =SUM(J7:J12) | ... Z13: =SUM(Z7:Z12) | AA13: =SUM(C13:N13) | AB13: =SUM(O13:Z13)
B14: Cloud/LLM/support | C14: ='04_Deploy'!D6*'01_Assumptions'!$D$15 | D14: ='04_Deploy'!D7*'01_Assumptions'!$D$15 | E14: ='04_Deploy'!D8*'01_Assumptions'!$D$15 | F14: ='04_Deploy'!D9*'01_Assumptions'!$D$15 | G14: ='04_Deploy'!D10*'01_Assumptions'!$D$15 | H14: ='04_Deploy'!D11*'01_Assumptions'!$D$15 | I14: ='04_Deploy'!D12*'01_Assumptions'!$D$15 | J14: ='04_Deploy'!D13*'01_Assumptions'!$D$15 | K14: ='04_Deploy'!D14*'01_Assumptions'!$D$15 | L14: ='04_Deploy'!D15*'01_Assumptions'!$D$15 | M14: ='04_Deploy'!D16*'01_Assumptions'!$D$15 | N14: ='04_Deploy'!D17*'01_Assumptions'!$D$15 | O14: ='04_Deploy'!D18*'01_Assumptions'!$D$15 | P14: ='04_Deploy'!D19*'01_Assumptions'!$D$15 | Q14: ='04_Deploy'!D20*'01_Assumptions'!$D$15 | R14: ='04_Deploy'!D21*'01_Assumptions'!$D$15 | S14: ='04_Deploy'!D22*'01_Assumptions'!$D$15 | T14: ='04_Deploy'!D23*'01_Assumptions'!$D$15 | U14: ='04_Deploy'!D24*'01_Assumptions'!$D$15 | V14: ='04_Deploy'!D25*'01_Assumptions'!$D$15 | W14: ='04_Deploy'!D26*'01_Assumptions'!$D$15 | X14: ='04_Deploy'!D27*'01_Assumptions'!$D$15 | Y14: ='04_Deploy'!D28*'01_Assumptions'!$D$15 | Z14: ='04_Deploy'!D29*'01_Assumptions'!$D$15 | AA14: =SUM(C14:N14) | AB14: =SUM(O14:Z14)
B15: Hardware replacement reserve | C15: ='04_Deploy'!I6*'01_Assumptions'!$D$16 | D15: ='04_Deploy'!I7*'01_Assumptions'!$D$16 | E15: ='04_Deploy'!I8*'01_Assumptions'!$D$16 | F15: ='04_Deploy'!I9*'01_Assumptions'!$D$16 | G15: ='04_Deploy'!I10*'01_Assumptions'!$D$16 | H15: ='04_Deploy'!I11*'01_Assumptions'!$D$16 | I15: ='04_Deploy'!I12*'01_Assumptions'!$D$16 | J15: ='04_Deploy'!I13*'01_Assumptions'!$D$16 | K15: ='04_Deploy'!I14*'01_Assumptions'!$D$16 | L15: ='04_Deploy'!I15*'01_Assumptions'!$D$16 | M15: ='04_Deploy'!I16*'01_Assumptions'!$D$16 | N15: ='04_Deploy'!I17*'01_Assumptions'!$D$16 | O15: ='04_Deploy'!I18*'01_Assumptions'!$D$16 | P15: ='04_Deploy'!I19*'01_Assumptions'!$D$16 | Q15: ='04_Deploy'!I20*'01_Assumptions'!$D$16 | R15: ='04_Deploy'!I21*'01_Assumptions'!$D$16 | S15: ='04_Deploy'!I22*'01_Assumptions'!$D$16 | T15: ='04_Deploy'!I23*'01_Assumptions'!$D$16 | U15: ='04_Deploy'!I24*'01_Assumptions'!$D$16 | V15: ='04_Deploy'!I25*'01_Assumptions'!$D$16 | W15: ='04_Deploy'!I26*'01_Assumptions'!$D$16 | X15: ='04_Deploy'!I27*'01_Assumptions'!$D$16 | Y15: ='04_Deploy'!I28*'01_Assumptions'!$D$16 | Z15: ='04_Deploy'!I29*'01_Assumptions'!$D$16 | AA15: =SUM(C15:N15) | AB15: =SUM(O15:Z15)
B16: Total COGS | C16: =SUM(C14:C15) | D16: =SUM(D14:D15) | E16: =SUM(E14:E15) | F16: =SUM(F14:F15) | G16: =SUM(G14:G15) | H16: =SUM(H14:H15) | I16: =SUM(I14:I15) | J16: =SUM(J14:J15) | ... Z16: =SUM(Z14:Z15) | AA16: =SUM(C16:N16) | AB16: =SUM(O16:Z16)
B17: Gross profit | C17: =SUM(C7:C13)-C16 | D17: =SUM(D7:D13)-D16 | E17: =SUM(E7:E13)-E16 | F17: =SUM(F7:F13)-F16 | G17: =SUM(G7:G13)-G16 | H17: =SUM(H7:H13)-H16 | I17: =SUM(I7:I13)-I16 | J17: =SUM(J7:J13)-J16 | ... Z17: =SUM(Z7:Z13)-Z16 | AA17: =SUM(C17:N17) | AB17: =SUM(O17:Z17)
B18: Payroll/contractors | C18: ='01_Assumptions'!$D$19*(1+IF(C$5="M1",0,IF(COLUMN()<=14,0,'01_Assumptions'!$D$22)) | D18: ='01_Assumptions'!$D$19*(1+IF(D$5="M1",0,IF(COLUMN()<=14,0,'01_Assumptions'!$D$22)) | E18: ='01_Assumptions'!$D$19*(1+IF(E$5="M1",0,IF(COLUMN()<=14,0,'01_Assumptions'!$D$22)) | F18: ='01_Assumptions'!$D$19*(1+IF(F$5="M1",0,IF(COLUMN()<=14,0,'01_Assumptions'!$D$22)) | G18: ='01_Assumptions'!$D$19*(1+IF(G$5="M1",0,IF(COLUMN()<=14,0,'01_Assumptions'!$D$22)) | H18: ='01_Assumptions'!$D$19*(1+IF(H$5="M1",0,IF(COLUMN()<=14,0,'01_Assumptions'!$D$22)) | I18: ='01_Assumptions'!$D$19*(1+IF(I$5="M1",0,IF(COLUMN()<=14,0,'01_Assumptions'!$D$22)) | J18: ='01_Assumptions'!$D$19*(1+IF(J$5="M1",0,IF(COLUMN()<=14,0,'01_Assumptions'!$D$22)) | ... Z18: ='01_Assumptions'!$D$19*(1+IF(Z$5="M1",0,IF(COLUMN()<=14,0,'01_Assumptions'!$D$22)) | AA18: =SUM(C18:N18) | AB18: =SUM(O18:Z18)
B19: Sales & marketing | C19: ='01_Assumptions'!$D$20*(1+IF(COLUMN()<=14,0,'01_Assumptions'!$D$22)) | D19: ='01_Assumptions'!$D$20*(1+IF(COLUMN()<=14,0,'01_Assumptions'!$D$22)) | E19: ='01_Assumptions'!$D$20*(1+IF(COLUMN()<=14,0,'01_Assumptions'!$D$22)) | F19: ='01_Assumptions'!$D$20*(1+IF(COLUMN()<=14,0,'01_Assumptions'!$D$22)) | G19: ='01_Assumptions'!$D$20*(1+IF(COLUMN()<=14,0,'01_Assumptions'!$D$22)) | H19: ='01_Assumptions'!$D$20*(1+IF(COLUMN()<=14,0,'01_Assumptions'!$D$22)) | I19: ='01_Assumptions'!$D$20*(1+IF(COLUMN()<=14,0,'01_Assumptions'!$D$22)) | J19: ='01_Assumptions'!$D$20*(1+IF(COLUMN()<=14,0,'01_Assumptions'!$D$22)) | ... Z19: ='01_Assumptions'!$D$20*(1+IF(COLUMN()<=14,0,'01_Assumptions'!$D$22)) | AA19: =SUM(C19:N19) | AB19: =SUM(O19:Z19)
B20: G&A/legal/insurance | C20: ='01_Assumptions'!$D$21*(1+IF(COLUMN()<=14,0,'01_Assumptions'!$D$22)) | D20: ='01_Assumptions'!$D$21*(1+IF(COLUMN()<=14,0,'01_Assumptions'!$D$22)) | E20: ='01_Assumptions'!$D$21*(1+IF(COLUMN()<=14,0,'01_Assumptions'!$D$22)) | F20: ='01_Assumptions'!$D$21*(1+IF(COLUMN()<=14,0,'01_Assumptions'!$D$22)) | G20: ='01_Assumptions'!$D$21*(1+IF(COLUMN()<=14,0,'01_Assumptions'!$D$22)) | H20: ='01_Assumptions'!$D$21*(1+IF(COLUMN()<=14,0,'01_Assumptions'!$D$22)) | I20: ='01_Assumptions'!$D$21*(1+IF(COLUMN()<=14,0,'01_Assumptions'!$D$22)) | J20: ='01_Assumptions'!$D$21*(1+IF(COLUMN()<=14,0,'01_Assumptions'!$D$22)) | ... Z20: ='01_Assumptions'!$D$21*(1+IF(COLUMN()<=14,0,'01_Assumptions'!$D$22)) | AA20: =SUM(C20:N20) | AB20: =SUM(O20:Z20)
B21: Total OPEX | C21: =SUM(C18:C20) | D21: =SUM(D18:D20) | E21: =SUM(E18:E20) | F21: =SUM(F18:F20) | G21: =SUM(G18:G20) | H21: =SUM(H18:H20) | I21: =SUM(I18:I20) | J21: =SUM(J18:J20) | ... Z21: =SUM(Z18:Z20) | AA21: =SUM(C21:N21) | AB21: =SUM(O21:Z21)
B22: EBITDA | C22: =C17-C21 | D22: =D17-D21 | E22: =E17-E21 | F22: =F17-F21 | G22: =G17-G21 | H22: =H17-H21 | I22: =I17-I21 | J22: =J17-J21 | ... Z22: =Z17-Z21 | AA22: =SUM(C22:N22) | AB22: =SUM(O22:Z22)

Sheet 06_Cashflow
B2: Cash flow / Flusso di cassa / Cash Flow
B3: Working-capital-aware monthly cash forecast. Funding need is the maximum cumulative deficit.
B5: Line item | C5: M1 | D5: M2 | E5: M3 | F5: M4 | G5: M5 | H5: M6 | I5: M7 | J5: M8 | K5: M9 | L5: M10 | M5: M11 | N5: M12 | O5: M13 | P5: M14 | Q5: M15 | R5: M16 | S5: M17 | T5: M18 | U5: M19 | V5: M20 | W5: M21 | X5: M22 | Y5: M23 | Z5: M24 | AA5: Y1 | AB5: Y2
B6: Opening cash | C6: 0 | D6: =C15 | E6: =D15 | F6: =E15 | G6: =F15 | H6: =G15 | I6: =H15 | J6: =I15 | K6: =J15 | ... Z6: =Y15 | AA6: =SUM(C6:N6) | AB6: =SUM(O6:Z6)
B7: Customer receipts: setup | C7: ='05_P&L'!C7*'01_Assumptions'!$D$18 | D7: ='05_P&L'!D7*'01_Assumptions'!$D$18 | E7: ='05_P&L'!E7*'01_Assumptions'!$D$18 | F7: ='05_P&L'!F7*'01_Assumptions'!$D$18 | G7: ='05_P&L'!G7*'01_Assumptions'!$D$18 | H7: ='05_P&L'!H7*'01_Assumptions'!$D$18 | I7: ='05_P&L'!I7*'01_Assumptions'!$D$18 | J7: ='05_P&L'!J7*'01_Assumptions'!$D$18 | ... Z7: ='05_P&L'!Z7*'01_Assumptions'!$D$18 | AA7: =SUM(C7:N7) | AB7: =SUM(O7:Z7)
B8: Customer receipts: recurring | C8: =('05_P&L'!C8+'05_P&L'!C9+'05_P&L'!C10+'05_P&L'!C11+'05_P&L'!C12)+('05_P&L'!C7*(1-'01_Assumptions'!$D$18)) | D8: =('05_P&L'!D8+'05_P&L'!D9+'05_P&L'!D10+'05_P&L'!D11+'05_P&L'!D12)+('05_P&L'!D7*(1-'01_Assumptions'!$D$18)) | E8: =('05_P&L'!E8+'05_P&L'!E9+'05_P&L'!E10+'05_P&L'!E11+'05_P&L'!E12)+('05_P&L'!E7*(1-'01_Assumptions'!$D$18)) | F8: =('05_P&L'!F8+'05_P&L'!F9+'05_P&L'!F10+'05_P&L'!F11+'05_P&L'!F12)+('05_P&L'!F7*(1-'01_Assumptions'!$D$18)) | G8: =('05_P&L'!G8+'05_P&L'!G9+'05_P&L'!G10+'05_P&L'!G11+'05_P&L'!G12)+('05_P&L'!G7*(1-'01_Assumptions'!$D$18)) | H8: =('05_P&L'!H8+'05_P&L'!H9+'05_P&L'!H10+'05_P&L'!H11+'05_P&L'!H12)+('05_P&L'!H7*(1-'01_Assumptions'!$D$18)) | I8: =('05_P&L'!I8+'05_P&L'!I9+'05_P&L'!I10+'05_P&L'!I11+'05_P&L'!I12)+('05_P&L'!I7*(1-'01_Assumptions'!$D$18)) | J8: =('05_P&L'!J8+'05_P&L'!J9+'05_P&L'!J10+'05_P&L'!J11+'05_P&L'!J12)+('05_P&L'!J7*(1-'01_Assumptions'!$D$18)) | ... Z8: =('05_P&L'!Z8+'05_P&L'!Z9+'05_P&L'!Z10+'05_P&L'!Z11+'05_P&L'!Z12)+('05_P&L'!Z7*(1-'01_Assumptions'!$D$18)) | AA8: =SUM(C8:N8) | AB8: =SUM(O8:Z8)
B9: Total cash in | C9: =SUM(C7:C8) | D9: =SUM(D7:D8) | E9: =SUM(E7:E8) | F9: =SUM(F7:F8) | G9: =SUM(G7:G8) | H9: =SUM(H7:H8) | I9: =SUM(I7:I8) | J9: =SUM(J7:J8) | ... Z9: =SUM(Z7:Z8) | AA9: =SUM(C9:N9) | AB9: =SUM(O9:Z9)
B10: Hardware purchase cash out | C10: ='04_Deploy'!I6*'01_Assumptions'!$D$19 | D10: ='04_Deploy'!I7*'01_Assumptions'!$D$19 | E10: ='04_Deploy'!I8*'01_Assumptions'!$D$19 | F10: ='04_Deploy'!I9*'01_Assumptions'!$D$19 | G10: ='04_Deploy'!I10*'01_Assumptions'!$D$19 | H10: ='04_Deploy'!I11*'01_Assumptions'!$D$19 | I10: ='04_Deploy'!I12*'01_Assumptions'!$D$19 | J10: ='04_Deploy'!I13*'01_Assumptions'!$D$19 | K10: ='04_Deploy'!I14*'01_Assumptions'!$D$19 | L10: ='04_Deploy'!I15*'01_Assumptions'!$D$19 | M10: ='04_Deploy'!I16*'01_Assumptions'!$D$19 | N10: ='04_Deploy'!I17*'01_Assumptions'!$D$19 | O10: ='04_Deploy'!I18*'01_Assumptions'!$D$19 | P10: ='04_Deploy'!I19*'01_Assumptions'!$D$19 | Q10: ='04_Deploy'!I20*'01_Assumptions'!$D$19 | R10: ='04_Deploy'!I21*'01_Assumptions'!$D$19 | S10: ='04_Deploy'!I22*'01_Assumptions'!$D$19 | T10: ='04_Deploy'!I23*'01_Assumptions'!$D$19 | U10: ='04_Deploy'!I24*'01_Assumptions'!$D$19 | V10: ='04_Deploy'!I25*'01_Assumptions'!$D$19 | W10: ='04_Deploy'!I26*'01_Assumptions'!$D$19 | X10: ='04_Deploy'!I27*'01_Assumptions'!$D$19 | Y10: ='04_Deploy'!I28*'01_Assumptions'!$D$19 | Z10: ='04_Deploy'!I29*'01_Assumptions'!$D$19 | AA10: =SUM(C10:N10) | AB10: =SUM(O10:Z10)
B11: COGS cash out | C11: ='05_P&L'!C16 | D11: ='05_P&L'!D16 | E11: ='05_P&L'!E16 | F11: ='05_P&L'!F16 | G11: ='05_P&L'!G16 | H11: ='05_P&L'!H16 | I11: ='05_P&L'!I16 | J11: ='05_P&L'!J16 | ... Z11: ='05_P&L'!Z16 | AA11: =SUM(C11:N11) | AB11: =SUM(O11:Z11)
B12: OPEX cash out | C12: ='05_P&L'!C21 | D12: ='05_P&L'!D21 | E12: ='05_P&L'!E21 | F12: ='05_P&L'!F21 | G12: ='05_P&L'!G21 | H12: ='05_P&L'!H21 | I12: ='05_P&L'!I21 | J12: ='05_P&L'!J21 | ... Z12: ='05_P&L'!Z21 | AA12: =SUM(C12:N12) | AB12: =SUM(O12:Z12)
B13: Total cash out | C13: =SUM(C10:C12) | D13: =SUM(D10:D12) | E13: =SUM(E10:E12) | F13: =SUM(F10:F12) | G13: =SUM(G10:G12) | H13: =SUM(H10:H12) | I13: =SUM(I10:I12) | J13: =SUM(J10:J12) | ... Z13: =SUM(Z10:Z12) | AA13: =SUM(C13:N13) | AB13: =SUM(O13:Z13)
B14: Net cash flow | C14: =C9-C13 | D14: =D9-D13 | E14: =E9-E13 | F14: =F9-F13 | G14: =G9-G13 | H14: =H9-H13 | I14: =I9-I13 | J14: =J9-J13 | ... Z14: =Z9-Z13 | AA14: =SUM(C14:N14) | AB14: =SUM(O14:Z14)
B15: Closing cash | C15: =C6+C14 | D15: =D6+D14 | E15: =E6+E14 | F15: =F6+F14 | G15: =G6+G14 | H15: =H6+H14 | I15: =I6+I14 | J15: =J6+J14 | ... Z15: =Z6+Z14 | AA15: =SUM(C15:N15) | AB15: =SUM(O15:Z15)
B16: Funding need | C16: =MAX(0,-C15) | D16: =MAX(0,-D15) | E16: =MAX(0,-E15) | F16: =MAX(0,-F15) | G16: =MAX(0,-G15) | H16: =MAX(0,-H15) | I16: =MAX(0,-I15) | J16: =MAX(0,-J15) | ... Z16: =MAX(0,-Z15) | AA16: =SUM(C16:N16) | AB16: =SUM(O16:Z16)

Sheet 07_Risks
B2: Риски / Rischi / Risks
B3: Risk register with mitigations and funding gates.
B5: Риск | C5: Вероятность | D5: Влияние | E5: Mitigation | F5: Gate
B6: Hotel sales cycle | C6: High | D6: High | E6: Paid pilot, partner channel, deposits before PO | F6: Pipeline: 3 pilots before inventory
B7: PMS fragmentation | C7: High | D7: High | E7: Support 2–3 PMS first; adapter architecture | F7: Two live integrations
B8: Hardware CE/RED/CRA | C8: Medium | D8: Very high | E8: Supplier technical-file audit; EU legal review; replacement pool | F8: No PO before documentation
B9: Privacy/identity | C9: Medium | D9: Very high | E9: No document storage; tokenised session; DPIA/DPA | F9: DPIA complete before pilot
B10: Seasonality | C10: High | D10: High | E10: Annual contracts; install off-season; Genova mix | F10: 12-month contracts
B11: Working capital | C11: Medium | D11: High | E11: Customer upfront payments; leased hardware; low MOQ | F11: Funding runway 12 months
B12: Usage/low adoption | C12: Medium | D12: High | E12: Lobby-first; QR fallback; instrument usage | F12: Weekly active guest target
B13: Vape regulation | C13: High | D13: Very high | E13: Licensed operator only; separate entity economics | F13: No direct sale without written advice
B14: Robot economics | C14: High | D14: Medium | E14: Robot-agnostic API before hardware purchase | F14: Task volume validated

Sheet 08_Sources
B2: Источники / Fonti / Sources
B3: Primary/official sources used for market and regulatory facts.
B5: Area | C5: Source | D5: Use | E5: URL
B6: Market | C6: Regione Liguria, Turismo in Liguria — Anno 2025 | D6: 2025 arrivals/presences/province | E6: https://www.regione.liguria.it/components/com_publiccompetitions/includes/download.php?id=77345:flussi-turismo-2025.pdf
B7: Market | C7: Istat, Capacità degli esercizi ricettivi | D7: Capacity data methodology, year 2025 | E7: https://www.istat.it/informazioni-sulla-rilevazione/capacita-degli-esercizi-ricettivi/
B8: EU IoT | C8: European Commission, Radio Equipment Directive | D8: RED cybersecurity and CRA interaction | E8: https://single-market-economy.ec.europa.eu/sectors/electrical-and-electronic-engineering-industries-eei/radio-equipment-directive_en
B9: EU IoT | C9: European Commission, Cyber Resilience Act | D9: Importer obligations and dates | E9: https://digital-strategy.ec.europa.eu/en/policies/cra-summary
B10: Privacy | C10: Garante per la protezione dei dati personali | D10: Hotel ID document retention | E10: https://www.garanteprivacy.it/home/docweb/-/docweb-display/docweb/10244195
B11: Tobacco | C11: Agenzia delle dogane e dei Monopoli | D11: Tobacco authorisation | E11: https://www.adm.gov.it/portale/en/sdg/tabacchi5
