Workbook

Sheet Сводка
B2: Модель запуска в Лигурии: hardware + agent-сервисы для отелей (EUR, без НДС)
B3: ВСЕ финансовые входные данные на листе «Допущения» — плановые заглушки (синие), НЕ котировки поставщиков и НЕ проверенные рыночные данные. Заменить реальными предложениями до любого инвестиционного решения.
B5: Показатель | C5: Значение
B6: Активный сценарий | C6: =CHOOSE('Допущения'!C5,"Lean","Base","Regional")
B7: Выручка, год 1 | C7: ='PnL'!AB8
B8: Выручка, год 2 | C8: ='PnL'!AC8
B9: EBITDA, год 1 | C9: ='PnL'!AB15
B10: EBITDA, год 2 | C10: ='PnL'!AC15
B11: Чистый результат за 24 мес. | C11: ='PnL'!AD17
B12: Первый месяц с EBITDA > 0 | C12: =IF(MIN('PnL'!D19:AA19)=99,"н/д",MIN('PnL'!D19:AA19))
B13: Пиковая потребность в финансировании | C13: =MAX(0,-MIN('Cashflow'!D14:AA14))
B14: Минимальный остаток денег | C14: =MIN('Cashflow'!D13:AA13)
B15: Активные объекты, месяц 12 | C15: ='Модель'!O5
B16: Активные объекты, месяц 24 | C16: ='Модель'!AA5
B17: Run-rate recurring+txn x12, месяц 24 | C17: =('PnL'!AA6+'PnL'!AA7)*12
B18: Валовая маржа, год 2 | C18: ='PnL'!AC12
B21: Index
B22: Допущения
B23: Сценарии
B24: Модель
B25: PnL
B26: Cashflow
B27: Экон_категорий
B28: Лицензии
B29: Риски
B30: Долговечность
B31: Примечания

Sheet Допущения
B2: Модель запуска в Лигурии: hardware + agent-сервисы для отелей (EUR, без НДС)
B3: ВСЕ финансовые входные данные на листе «Допущения» — плановые заглушки (синие), НЕ котировки поставщиков и НЕ проверенные рыночные данные. Заменить реальными предложениями до любого инвестиционного решения.
B4: Общие параметры
B5: Сценарий (1=Lean, 2=Base, 3=Regional) | C5: 2
B6: Месячный churn объектов | C6: 0.008
B7: Стартовый капитал, EUR | C7: 60000
B8: Налог на положительный месячный результат (упрощённо IRES+IRAP) | C8: 0.279
B9: Доля выручки, собираемая в том же месяце | C9: 0.5
B14: Категория | C14: Landed-стоимость HW / ед. | D14: Установка / настройка / ед. | E14: Разовая цена / ед. | F14: Ежемесячно (SaaS/lease) / ед. | G14: Маржа транзакций / мес / ед. | H14: Перем. затраты / мес / ед. | I14: Ед. на объект | J14: Attach rate (доля новых объектов) | K14: Месяц запуска | L14: ID
B15: Hotel Agent OS (платформа агентов) | C15: 0 | D15: 600 | E15: 1500 | F15: 250 | G15: 0 | H15: 60 | I15: 1 | J15: 1 | K15: 1 | L15: C01
B16: GuestNode Lobby (ресепшен) | C16: 280 | D16: 60 | E16: 590 | F16: 40 | G16: 15 | H16: 8 | I16: 1 | J16: 0.5 | K16: 3 | L16: C02
B17: GuestNode в номере | C17: 95 | D17: 15 | E17: 180 | F17: 6 | G17: 0 | H17: 2.5 | I17: 12 | J17: 0.2 | K17: 6 | L17: C03
B18: Smart Travel Wall (микро-магазин) | C18: 2800 | D18: 250 | E18: 4200 | F18: 60 | G18: 150 | H18: 40 | I18: 1 | J18: 0.25 | K18: 4 | L18: C04
B19: Rental-локеры | C19: 900 | D19: 120 | E19: 1500 | F19: 20 | G19: 60 | H19: 10 | I19: 1 | J19: 0.25 | K19: 4 | L19: C05
B20: Локеры для багажа | C20: 1800 | D20: 200 | E20: 2800 | F20: 25 | G20: 90 | H20: 10 | I20: 1 | J20: 0.15 | K20: 6 | L20: C06
B21: Аренда power bank | C21: 700 | D21: 60 | E21: 1100 | F21: 15 | G21: 45 | H21: 12 | I21: 1 | J21: 0.15 | K21: 6 | L21: C07
B22: IoT-комплект энергосбережения (на номер) | C22: 70 | D22: 25 | E22: 140 | F22: 3 | G22: 0 | H22: 0.8 | I22: 25 | J22: 0.3 | K22: 3 | L22: C08
B23: Smart access (на дверь) | C23: 130 | D23: 40 | E23: 260 | F23: 2 | G23: 0 | H23: 0.5 | I23: 15 | J23: 0.15 | K23: 8 | L23: C09
B24: Датчики Healthy Room (на номер) | C24: 45 | D24: 10 | E24: 90 | F24: 1.5 | G24: 0 | H24: 0.4 | I24: 15 | J24: 0.1 | K24: 9 | L24: C10
B25: Киоск check-in / ID | C25: 1500 | D25: 150 | E25: 2600 | F25: 50 | G25: 10 | H25: 15 | I25: 1 | J25: 0.1 | K25: 8 | L25: C11
B26: Локальный marketplace | C26: 0 | D26: 0 | E26: 0 | F26: 0 | G26: 120 | H26: 5 | I26: 1 | J26: 0.4 | K26: 5 | L26: C12
... B29: Регулируемый vending (только fee лицензированного партнёра) | C29: 0 | D29: 0 | E29: 0 | F29: 0 | G29: 80 | H29: 10 | I29: 1 | J29: 0 | K29: 12 | L29: C15
B32: Постоянные ежемесячные расходы
B33: Категория | C33: EUR / мес | D33: Месяц старта
B34: Founder/FDE-инженер | C34: 3500 | D34: 1
B35: Продажи и партнёрства (part-time) | C35: 2000 | D35: 3
B36: Монтажник/поддержка (подряд) | C36: 1500 | D36: 4
B37: Cloud + LLM (база) | C37: 400 | D37: 1
B38: Юристы, compliance, бухгалтерия | C38: 900 | D38: 1
B39: Маркетинг и выставки | C39: 800 | D39: 1
B40: Страхование | C40: 250 | D40: 2
B41: Склад/офис | C41: 400 | D41: 2
B42: Поездки | C42: 500 | D42: 1
B45: Разовые расходы запуска (месяц 1)
B46: Предсертификационный аудит CE/RED/EMC | C46: 6000
B47: Пробные партии у OEM | C47: 5000
B48: Юр. подготовка (контракты, GDPR/DPA) | C48: 4000
B49: Демо-комплект | C49: 3500
B50: Бренд и сайт | C50: 2000

Sheet Сценарии
B2: Новые объекты / мес
B4: Месяц | C4: 1 | D4: 2 | E4: 3 | F4: 4 | G4: 5 | H4: 6 | I4: 7 | J4: 8 | K4: 9 | L4: 10 | M4: 11 | N4: 12 | O4: 13 | P4: 14 | Q4: 15 | R4: 16 | S4: 17 | T4: 18 | U4: 19 | V4: 20 | W4: 21 | X4: 22 | Y4: 23 | Z4: 24
B5: Lean | C5: 0 | D5: 0 | E5: 1 | F5: 1 | G5: 1 | H5: 1 | I5: 1 | J5: 1 | K5: 1 | L5: 1 | M5: 1 | N5: 1 | O5: 2 | P5: 2 | Q5: 2 | R5: 2 | S5: 2 | T5: 2 | U5: 2 | V5: 2 | W5: 2 | X5: 2 | Y5: 2 | Z5: 2
B6: Base | C6: 0 | D6: 0 | E6: 2 | F6: 2 | G6: 2 | H6: 2 | I6: 4 | J6: 4 | K6: 4 | L6: 4 | M6: 4 | N6: 4 | O6: 4 | P6: 4 | Q6: 4 | R6: 4 | S6: 4 | T6: 4 | U6: 4 | V6: 4 | W6: 4 | X6: 4 | Y6: 4 | Z6: 4
B7: Regional | C7: 0 | D7: 0 | E7: 4 | F7: 4 | G7: 4 | H7: 4 | I7: 8 | J7: 8 | K7: 8 | L7: 8 | M7: 8 | N7: 8 | O7: 8 | P7: 8 | Q7: 8 | R7: 8 | S7: 8 | T7: 8 | U7: 8 | V7: 8 | W7: 8 | X7: 8 | Y7: 8 | Z7: 8
B8: Выбранный сценарий | C8: =CHOOSE('Допущения'!$C$5,C5,C6,C7) | D8: =CHOOSE('Допущения'!$C$5,D5,D6,D7) | E8: =CHOOSE('Допущения'!$C$5,E5,E6,E7) | F8: =CHOOSE('Допущения'!$C$5,F5,F6,F7) | G8: =CHOOSE('Допущения'!$C$5,G5,G6,G7) | H8: =CHOOSE('Допущения'!$C$5,H5,H6,H7) | I8: =CHOOSE('Допущения'!$C$5,I5,I6,I7) | J8: =CHOOSE('Допущения'!$C$5,J5,J6,J7) | ... Z8: =CHOOSE('Допущения'!$C$5,Z5,Z6,Z7)

Sheet Модель
B1: Модель запуска в Лигурии: hardware + agent-сервисы для отелей (EUR, без НДС)
A3: ID | B3: Категория | C3: metric | D3: 1 | E3: 2 | F3: 3 | G3: 4 | H3: 5 | I3: 6 | J3: 7 | K3: 8 | L3: 9 | M3: 10 | N3: 11 | O3: 12 | P3: 13 | Q3: 14 | R3: 15 | S3: 16 | T3: 17 | U3: 18 | V3: 19 | W3: 20 | X3: 21 | Y3: 22 | Z3: 23 | AA3: 24 | AB3: 24 мес.
B4: Новые объекты / мес | D4: ='Сценарии'!C8 | E4: ='Сценарии'!D8 | F4: ='Сценарии'!E8 | G4: ='Сценарии'!F8 | H4: ='Сценарии'!G8 | I4: ='Сценарии'!H8 | J4: ='Сценарии'!I8 | K4: ='Сценарии'!J8 | ... AA4: ='Сценарии'!Z8
B5: Активные объекты | D5: =D4 | E5: =D5*(1-'Допущения'!$C$6)+E4 | F5: =E5*(1-'Допущения'!$C$6)+F4 | G5: =F5*(1-'Допущения'!$C$6)+G4 | H5: =G5*(1-'Допущения'!$C$6)+H4 | I5: =H5*(1-'Допущения'!$C$6)+I4 | J5: =I5*(1-'Допущения'!$C$6)+J4 | K5: =J5*(1-'Допущения'!$C$6)+K4 | L5: =K5*(1-'Допущения'!$C$6)+L4 | ... AA5: =Z5*(1-'Допущения'!$C$6)+AA4
A7: C01 | B7: Hotel Agent OS (платформа агентов) | C7: NEWU | D7: =IF(D$3>='Допущения'!$K$15,D$4*'Допущения'!$J$15*'Допущения'!$I$15,0) | E7: =IF(E$3>='Допущения'!$K$15,E$4*'Допущения'!$J$15*'Допущения'!$I$15,0) | F7: =IF(F$3>='Допущения'!$K$15,F$4*'Допущения'!$J$15*'Допущения'!$I$15,0) | G7: =IF(G$3>='Допущения'!$K$15,G$4*'Допущения'!$J$15*'Допущения'!$I$15,0) | H7: =IF(H$3>='Допущения'!$K$15,H$4*'Допущения'!$J$15*'Допущения'!$I$15,0) | I7: =IF(I$3>='Допущения'!$K$15,I$4*'Допущения'!$J$15*'Допущения'!$I$15,0) | J7: =IF(J$3>='Допущения'!$K$15,J$4*'Допущения'!$J$15*'Допущения'!$I$15,0) | K7: =IF(K$3>='Допущения'!$K$15,K$4*'Допущения'!$J$15*'Допущения'!$I$15,0) | ... AA7: =IF(AA$3>='Допущения'!$K$15,AA$4*'Допущения'!$J$15*'Допущения'!$I$15,0) | AB7: =SUM(D7:AA7)
A8: C01 | B8: Hotel Agent OS (платформа агентов) | C8: ACTU | D8: =D7 | E8: =D8*(1-'Допущения'!$C$6)+E7 | F8: =E8*(1-'Допущения'!$C$6)+F7 | G8: =F8*(1-'Допущения'!$C$6)+G7 | H8: =G8*(1-'Допущения'!$C$6)+H7 | I8: =H8*(1-'Допущения'!$C$6)+I7 | J8: =I8*(1-'Допущения'!$C$6)+J7 | K8: =J8*(1-'Допущения'!$C$6)+K7 | L8: =K8*(1-'Допущения'!$C$6)+L7 | ... AA8: =Z8*(1-'Допущения'!$C$6)+AA7 | AB8: =SUM(D8:AA8)
A9: C01 | B9: Hotel Agent OS (платформа агентов) | C9: HWREV | D9: =D7*'Допущения'!$E$15 | E9: =E7*'Допущения'!$E$15 | F9: =F7*'Допущения'!$E$15 | G9: =G7*'Допущения'!$E$15 | H9: =H7*'Допущения'!$E$15 | I9: =I7*'Допущения'!$E$15 | J9: =J7*'Допущения'!$E$15 | K9: =K7*'Допущения'!$E$15 | ... AA9: =AA7*'Допущения'!$E$15 | AB9: =SUM(D9:AA9)
A10: C01 | B10: Hotel Agent OS (платформа агентов) | C10: RECREV | D10: =D8*'Допущения'!$F$15 | E10: =E8*'Допущения'!$F$15 | F10: =F8*'Допущения'!$F$15 | G10: =G8*'Допущения'!$F$15 | H10: =H8*'Допущения'!$F$15 | I10: =I8*'Допущения'!$F$15 | J10: =J8*'Допущения'!$F$15 | K10: =K8*'Допущения'!$F$15 | ... AA10: =AA8*'Допущения'!$F$15 | AB10: =SUM(D10:AA10)
A11: C01 | B11: Hotel Agent OS (платформа агентов) | C11: TXNREV | D11: =D8*'Допущения'!$G$15 | E11: =E8*'Допущения'!$G$15 | F11: =F8*'Допущения'!$G$15 | G11: =G8*'Допущения'!$G$15 | H11: =H8*'Допущения'!$G$15 | I11: =I8*'Допущения'!$G$15 | J11: =J8*'Допущения'!$G$15 | K11: =K8*'Допущения'!$G$15 | ... AA11: =AA8*'Допущения'!$G$15 | AB11: =SUM(D11:AA11)
A12: C01 | B12: Hotel Agent OS (платформа агентов) | C12: COGS | D12: =D7*('Допущения'!$C$15+'Допущения'!$D$15) | E12: =E7*('Допущения'!$C$15+'Допущения'!$D$15) | F12: =F7*('Допущения'!$C$15+'Допущения'!$D$15) | G12: =G7*('Допущения'!$C$15+'Допущения'!$D$15) | H12: =H7*('Допущения'!$C$15+'Допущения'!$D$15) | I12: =I7*('Допущения'!$C$15+'Допущения'!$D$15) | J12: =J7*('Допущения'!$C$15+'Допущения'!$D$15) | K12: =K7*('Допущения'!$C$15+'Допущения'!$D$15) | ... AA12: =AA7*('Допущения'!$C$15+'Допущения'!$D$15) | AB12: =SUM(D12:AA12)
A13: C01 | B13: Hotel Agent OS (платформа агентов) | C13: VARC | D13: =D8*'Допущения'!$H$15 | E13: =E8*'Допущения'!$H$15 | F13: =F8*'Допущения'!$H$15 | G13: =G8*'Допущения'!$H$15 | H13: =H8*'Допущения'!$H$15 | I13: =I8*'Допущения'!$H$15 | J13: =J8*'Допущения'!$H$15 | K13: =K8*'Допущения'!$H$15 | ... AA13: =AA8*'Допущения'!$H$15 | AB13: =SUM(D13:AA13)
A14: C02 | B14: GuestNode Lobby (ресепшен) | C14: NEWU | D14: =IF(D$3>='Допущения'!$K$16,D$4*'Допущения'!$J$16*'Допущения'!$I$16,0) | E14: =IF(E$3>='Допущения'!$K$16,E$4*'Допущения'!$J$16*'Допущения'!$I$16,0) | F14: =IF(F$3>='Допущения'!$K$16,F$4*'Допущения'!$J$16*'Допущения'!$I$16,0) | G14: =IF(G$3>='Допущения'!$K$16,G$4*'Допущения'!$J$16*'Допущения'!$I$16,0) | H14: =IF(H$3>='Допущения'!$K$16,H$4*'Допущения'!$J$16*'Допущения'!$I$16,0) | I14: =IF(I$3>='Допущения'!$K$16,I$4*'Допущения'!$J$16*'Допущения'!$I$16,0) | J14: =IF(J$3>='Допущения'!$K$16,J$4*'Допущения'!$J$16*'Допущения'!$I$16,0) | K14: =IF(K$3>='Допущения'!$K$16,K$4*'Допущения'!$J$16*'Допущения'!$I$16,0) | ... AA14: =IF(AA$3>='Допущения'!$K$16,AA$4*'Допущения'!$J$16*'Допущения'!$I$16,0) | AB14: =SUM(D14:AA14)
A15: C02 | B15: GuestNode Lobby (ресепшен) | C15: ACTU | D15: =D14 | E15: =D15*(1-'Допущения'!$C$6)+E14 | F15: =E15*(1-'Допущения'!$C$6)+F14 | G15: =F15*(1-'Допущения'!$C$6)+G14 | H15: =G15*(1-'Допущения'!$C$6)+H14 | I15: =H15*(1-'Допущения'!$C$6)+I14 | J15: =I15*(1-'Допущения'!$C$6)+J14 | K15: =J15*(1-'Допущения'!$C$6)+K14 | L15: =K15*(1-'Допущения'!$C$6)+L14 | ... AA15: =Z15*(1-'Допущения'!$C$6)+AA14 | AB15: =SUM(D15:AA15)
A16: C02 | B16: GuestNode Lobby (ресепшен) | C16: HWREV | D16: =D14*'Допущения'!$E$16 | E16: =E14*'Допущения'!$E$16 | F16: =F14*'Допущения'!$E$16 | G16: =G14*'Допущения'!$E$16 | H16: =H14*'Допущения'!$E$16 | I16: =I14*'Допущения'!$E$16 | J16: =J14*'Допущения'!$E$16 | K16: =K14*'Допущения'!$E$16 | ... AA16: =AA14*'Допущения'!$E$16 | AB16: =SUM(D16:AA16)
A17: C02 | B17: GuestNode Lobby (ресепшен) | C17: RECREV | D17: =D15*'Допущения'!$F$16 | E17: =E15*'Допущения'!$F$16 | F17: =F15*'Допущения'!$F$16 | G17: =G15*'Допущения'!$F$16 | H17: =H15*'Допущения'!$F$16 | I17: =I15*'Допущения'!$F$16 | J17: =J15*'Допущения'!$F$16 | K17: =K15*'Допущения'!$F$16 | ... AA17: =AA15*'Допущения'!$F$16 | AB17: =SUM(D17:AA17)
A18: C02 | B18: GuestNode Lobby (ресепшен) | C18: TXNREV | D18: =D15*'Допущения'!$G$16 | E18: =E15*'Допущения'!$G$16 | F18: =F15*'Допущения'!$G$16 | G18: =G15*'Допущения'!$G$16 | H18: =H15*'Допущения'!$G$16 | I18: =I15*'Допущения'!$G$16 | J18: =J15*'Допущения'!$G$16 | K18: =K15*'Допущения'!$G$16 | ... AA18: =AA15*'Допущения'!$G$16 | AB18: =SUM(D18:AA18)
A19: C02 | B19: GuestNode Lobby (ресепшен) | C19: COGS | D19: =D14*('Допущения'!$C$16+'Допущения'!$D$16) | E19: =E14*('Допущения'!$C$16+'Допущения'!$D$16) | F19: =F14*('Допущения'!$C$16+'Допущения'!$D$16) | G19: =G14*('Допущения'!$C$16+'Допущения'!$D$16) | H19: =H14*('Допущения'!$C$16+'Допущения'!$D$16) | I19: =I14*('Допущения'!$C$16+'Допущения'!$D$16) | J19: =J14*('Допущения'!$C$16+'Допущения'!$D$16) | K19: =K14*('Допущения'!$C$16+'Допущения'!$D$16) | ... AA19: =AA14*('Допущения'!$C$16+'Допущения'!$D$16) | AB19: =SUM(D19:AA19)
A20: C02 | B20: GuestNode Lobby (ресепшен) | C20: VARC | D20: =D15*'Допущения'!$H$16 | E20: =E15*'Допущения'!$H$16 | F20: =F15*'Допущения'!$H$16 | G20: =G15*'Допущения'!$H$16 | H20: =H15*'Допущения'!$H$16 | I20: =I15*'Допущения'!$H$16 | J20: =J15*'Допущения'!$H$16 | K20: =K15*'Допущения'!$H$16 | ... AA20: =AA15*'Допущения'!$H$16 | AB20: =SUM(D20:AA20)
A21: C03 | B21: GuestNode в номере | C21: NEWU | D21: =IF(D$3>='Допущения'!$K$17,D$4*'Допущения'!$J$17*'Допущения'!$I$17,0) | E21: =IF(E$3>='Допущения'!$K$17,E$4*'Допущения'!$J$17*'Допущения'!$I$17,0) | F21: =IF(F$3>='Допущения'!$K$17,F$4*'Допущения'!$J$17*'Допущения'!$I$17,0) | G21: =IF(G$3>='Допущения'!$K$17,G$4*'Допущения'!$J$17*'Допущения'!$I$17,0) | H21: =IF(H$3>='Допущения'!$K$17,H$4*'Допущения'!$J$17*'Допущения'!$I$17,0) | I21: =IF(I$3>='Допущения'!$K$17,I$4*'Допущения'!$J$17*'Допущения'!$I$17,0) | J21: =IF(J$3>='Допущения'!$K$17,J$4*'Допущения'!$J$17*'Допущения'!$I$17,0) | K21: =IF(K$3>='Допущения'!$K$17,K$4*'Допущения'!$J$17*'Допущения'!$I$17,0) | ... AA21: =IF(AA$3>='Допущения'!$K$17,AA$4*'Допущения'!$J$17*'Допущения'!$I$17,0) | AB21: =SUM(D21:AA21)
A22: C03 | B22: GuestNode в номере | C22: ACTU | D22: =D21 | E22: =D22*(1-'Допущения'!$C$6)+E21 | F22: =E22*(1-'Допущения'!$C$6)+F21 | G22: =F22*(1-'Допущения'!$C$6)+G21 | H22: =G22*(1-'Допущения'!$C$6)+H21 | I22: =H22*(1-'Допущения'!$C$6)+I21 | J22: =I22*(1-'Допущения'!$C$6)+J21 | K22: =J22*(1-'Допущения'!$C$6)+K21 | L22: =K22*(1-'Допущения'!$C$6)+L21 | ... AA22: =Z22*(1-'Допущения'!$C$6)+AA21 | AB22: =SUM(D22:AA22)
A23: C03 | B23: GuestNode в номере | C23: HWREV | D23: =D21*'Допущения'!$E$17 | E23: =E21*'Допущения'!$E$17 | F23: =F21*'Допущения'!$E$17 | G23: =G21*'Допущения'!$E$17 | H23: =H21*'Допущения'!$E$17 | I23: =I21*'Допущения'!$E$17 | J23: =J21*'Допущения'!$E$17 | K23: =K21*'Допущения'!$E$17 | ... AA23: =AA21*'Допущения'!$E$17 | AB23: =SUM(D23:AA23)
A24: C03 | B24: GuestNode в номере | C24: RECREV | D24: =D22*'Допущения'!$F$17 | E24: =E22*'Допущения'!$F$17 | F24: =F22*'Допущения'!$F$17 | G24: =G22*'Допущения'!$F$17 | H24: =H22*'Допущения'!$F$17 | I24: =I22*'Допущения'!$F$17 | J24: =J22*'Допущения'!$F$17 | K24: =K22*'Допущения'!$F$17 | ... AA24: =AA22*'Допущения'!$F$17 | AB24: =SUM(D24:AA24)
A25: C03 | B25: GuestNode в номере | C25: TXNREV | D25: =D22*'Допущения'!$G$17 | E25: =E22*'Допущения'!$G$17 | F25: =F22*'Допущения'!$G$17 | G25: =G22*'Допущения'!$G$17 | H25: =H22*'Допущения'!$G$17 | I25: =I22*'Допущения'!$G$17 | J25: =J22*'Допущения'!$G$17 | K25: =K22*'Допущения'!$G$17 | ... AA25: =AA22*'Допущения'!$G$17 | AB25: =SUM(D25:AA25)
A26: C03 | B26: GuestNode в номере | C26: COGS | D26: =D21*('Допущения'!$C$17+'Допущения'!$D$17) | E26: =E21*('Допущения'!$C$17+'Допущения'!$D$17) | F26: =F21*('Допущения'!$C$17+'Допущения'!$D$17) | G26: =G21*('Допущения'!$C$17+'Допущения'!$D$17) | H26: =H21*('Допущения'!$C$17+'Допущения'!$D$17) | I26: =I21*('Допущения'!$C$17+'Допущения'!$D$17) | J26: =J21*('Допущения'!$C$17+'Допущения'!$D$17) | K26: =K21*('Допущения'!$C$17+'Допущения'!$D$17) | ... AA26: =AA21*('Допущения'!$C$17+'Допущения'!$D$17) | AB26: =SUM(D26:AA26)
A27: C03 | B27: GuestNode в номере | C27: VARC | D27: =D22*'Допущения'!$H$17 | E27: =E22*'Допущения'!$H$17 | F27: =F22*'Допущения'!$H$17 | G27: =G22*'Допущения'!$H$17 | H27: =H22*'Допущения'!$H$17 | I27: =I22*'Допущения'!$H$17 | J27: =J22*'Допущения'!$H$17 | K27: =K22*'Допущения'!$H$17 | ... AA27: =AA22*'Допущения'!$H$17 | AB27: =SUM(D27:AA27)
A28: C04 | B28: Smart Travel Wall (микро-магазин) | C28: NEWU | D28: =IF(D$3>='Допущения'!$K$18,D$4*'Допущения'!$J$18*'Допущения'!$I$18,0) | E28: =IF(E$3>='Допущения'!$K$18,E$4*'Допущения'!$J$18*'Допущения'!$I$18,0) | F28: =IF(F$3>='Допущения'!$K$18,F$4*'Допущения'!$J$18*'Допущения'!$I$18,0) | G28: =IF(G$3>='Допущения'!$K$18,G$4*'Допущения'!$J$18*'Допущения'!$I$18,0) | H28: =IF(H$3>='Допущения'!$K$18,H$4*'Допущения'!$J$18*'Допущения'!$I$18,0) | I28: =IF(I$3>='Допущения'!$K$18,I$4*'Допущения'!$J$18*'Допущения'!$I$18,0) | J28: =IF(J$3>='Допущения'!$K$18,J$4*'Допущения'!$J$18*'Допущения'!$I$18,0) | K28: =IF(K$3>='Допущения'!$K$18,K$4*'Допущения'!$J$18*'Допущения'!$I$18,0) | ... AA28: =IF(AA$3>='Допущения'!$K$18,AA$4*'Допущения'!$J$18*'Допущения'!$I$18,0) | AB28: =SUM(D28:AA28)
A29: C04 | B29: Smart Travel Wall (микро-магазин) | C29: ACTU | D29: =D28 | E29: =D29*(1-'Допущения'!$C$6)+E28 | F29: =E29*(1-'Допущения'!$C$6)+F28 | G29: =F29*(1-'Допущения'!$C$6)+G28 | H29: =G29*(1-'Допущения'!$C$6)+H28 | I29: =H29*(1-'Допущения'!$C$6)+I28 | J29: =I29*(1-'Допущения'!$C$6)+J28 | K29: =J29*(1-'Допущения'!$C$6)+K28 | L29: =K29*(1-'Допущения'!$C$6)+L28 | ... AA29: =Z29*(1-'Допущения'!$C$6)+AA28 | AB29: =SUM(D29:AA29)
A30: C04 | B30: Smart Travel Wall (микро-магазин) | C30: HWREV | D30: =D28*'Допущения'!$E$18 | E30: =E28*'Допущения'!$E$18 | F30: =F28*'Допущения'!$E$18 | G30: =G28*'Допущения'!$E$18 | H30: =H28*'Допущения'!$E$18 | I30: =I28*'Допущения'!$E$18 | J30: =J28*'Допущения'!$E$18 | K30: =K28*'Допущения'!$E$18 | ... AA30: =AA28*'Допущения'!$E$18 | AB30: =SUM(D30:AA30)
A31: C04 | B31: Smart Travel Wall (микро-магазин) | C31: RECREV | D31: =D29*'Допущения'!$F$18 | E31: =E29*'Допущения'!$F$18 | F31: =F29*'Допущения'!$F$18 | G31: =G29*'Допущения'!$F$18 | H31: =H29*'Допущения'!$F$18 | I31: =I29*'Допущения'!$F$18 | J31: =J29*'Допущения'!$F$18 | K31: =K29*'Допущения'!$F$18 | ... AA31: =AA29*'Допущения'!$F$18 | AB31: =SUM(D31:AA31)
A32: C04 | B32: Smart Travel Wall (микро-магазин) | C32: TXNREV | D32: =D29*'Допущения'!$G$18 | E32: =E29*'Допущения'!$G$18 | F32: =F29*'Допущения'!$G$18 | G32: =G29*'Допущения'!$G$18 | H32: =H29*'Допущения'!$G$18 | I32: =I29*'Допущения'!$G$18 | J32: =J29*'Допущения'!$G$18 | K32: =K29*'Допущения'!$G$18 | ... AA32: =AA29*'Допущения'!$G$18 | AB32: =SUM(D32:AA32)
A33: C04 | B33: Smart Travel Wall (микро-магазин) | C33: COGS | D33: =D28*('Допущения'!$C$18+'Допущения'!$D$18) | E33: =E28*('Допущения'!$C$18+'Допущения'!$D$18) | F33: =F28*('Допущения'!$C$18+'Допущения'!$D$18) | G33: =G28*('Допущения'!$C$18+'Допущения'!$D$18) | H33: =H28*('Допущения'!$C$18+'Допущения'!$D$18) | I33: =I28*('Допущения'!$C$18+'Допущения'!$D$18) | J33: =J28*('Допущения'!$C$18+'Допущения'!$D$18) | K33: =K28*('Допущения'!$C$18+'Допущения'!$D$18) | ... AA33: =AA28*('Допущения'!$C$18+'Допущения'!$D$18) | AB33: =SUM(D33:AA33)
A34: C04 | B34: Smart Travel Wall (микро-магазин) | C34: VARC | D34: =D29*'Допущения'!$H$18 | E34: =E29*'Допущения'!$H$18 | F34: =F29*'Допущения'!$H$18 | G34: =G29*'Допущения'!$H$18 | H34: =H29*'Допущения'!$H$18 | I34: =I29*'Допущения'!$H$18 | J34: =J29*'Допущения'!$H$18 | K34: =K29*'Допущения'!$H$18 | ... AA34: =AA29*'Допущения'!$H$18 | AB34: =SUM(D34:AA34)
A35: C05 | B35: Rental-локеры | C35: NEWU | D35: =IF(D$3>='Допущения'!$K$19,D$4*'Допущения'!$J$19*'Допущения'!$I$19,0) | E35: =IF(E$3>='Допущения'!$K$19,E$4*'Допущения'!$J$19*'Допущения'!$I$19,0) | F35: =IF(F$3>='Допущения'!$K$19,F$4*'Допущения'!$J$19*'Допущения'!$I$19,0) | G35: =IF(G$3>='Допущения'!$K$19,G$4*'Допущения'!$J$19*'Допущения'!$I$19,0) | H35: =IF(H$3>='Допущения'!$K$19,H$4*'Допущения'!$J$19*'Допущения'!$I$19,0) | I35: =IF(I$3>='Допущения'!$K$19,I$4*'Допущения'!$J$19*'Допущения'!$I$19,0) | J35: =IF(J$3>='Допущения'!$K$19,J$4*'Допущения'!$J$19*'Допущения'!$I$19,0) | K35: =IF(K$3>='Допущения'!$K$19,K$4*'Допущения'!$J$19*'Допущения'!$I$19,0) | ... AA35: =IF(AA$3>='Допущения'!$K$19,AA$4*'Допущения'!$J$19*'Допущения'!$I$19,0) | AB35: =SUM(D35:AA35)
A36: C05 | B36: Rental-локеры | C36: ACTU | D36: =D35 | E36: =D36*(1-'Допущения'!$C$6)+E35 | F36: =E36*(1-'Допущения'!$C$6)+F35 | G36: =F36*(1-'Допущения'!$C$6)+G35 | H36: =G36*(1-'Допущения'!$C$6)+H35 | I36: =H36*(1-'Допущения'!$C$6)+I35 | J36: =I36*(1-'Допущения'!$C$6)+J35 | K36: =J36*(1-'Допущения'!$C$6)+K35 | L36: =K36*(1-'Допущения'!$C$6)+L35 | ... AA36: =Z36*(1-'Допущения'!$C$6)+AA35 | AB36: =SUM(D36:AA36)
A37: C05 | B37: Rental-локеры | C37: HWREV | D37: =D35*'Допущения'!$E$19 | E37: =E35*'Допущения'!$E$19 | F37: =F35*'Допущения'!$E$19 | G37: =G35*'Допущения'!$E$19 | H37: =H35*'Допущения'!$E$19 | I37: =I35*'Допущения'!$E$19 | J37: =J35*'Допущения'!$E$19 | K37: =K35*'Допущения'!$E$19 | ... AA37: =AA35*'Допущения'!$E$19 | AB37: =SUM(D37:AA37)
A38: C05 | B38: Rental-локеры | C38: RECREV | D38: =D36*'Допущения'!$F$19 | E38: =E36*'Допущения'!$F$19 | F38: =F36*'Допущения'!$F$19 | G38: =G36*'Допущения'!$F$19 | H38: =H36*'Допущения'!$F$19 | I38: =I36*'Допущения'!$F$19 | J38: =J36*'Допущения'!$F$19 | K38: =K36*'Допущения'!$F$19 | ... AA38: =AA36*'Допущения'!$F$19 | AB38: =SUM(D38:AA38)
A39: C05 | B39: Rental-локеры | C39: TXNREV | D39: =D36*'Допущения'!$G$19 | E39: =E36*'Допущения'!$G$19 | F39: =F36*'Допущения'!$G$19 | G39: =G36*'Допущения'!$G$19 | H39: =H36*'Допущения'!$G$19 | I39: =I36*'Допущения'!$G$19 | J39: =J36*'Допущения'!$G$19 | K39: =K36*'Допущения'!$G$19 | ... AA39: =AA36*'Допущения'!$G$19 | AB39: =SUM(D39:AA39)
A40: C05 | B40: Rental-локеры | C40: COGS | D40: =D35*('Допущения'!$C$19+'Допущения'!$D$19) | E40: =E35*('Допущения'!$C$19+'Допущения'!$D$19) | F40: =F35*('Допущения'!$C$19+'Допущения'!$D$19) | G40: =G35*('Допущения'!$C$19+'Допущения'!$D$19) | H40: =H35*('Допущения'!$C$19+'Допущения'!$D$19) | I40: =I35*('Допущения'!$C$19+'Допущения'!$D$19) | J40: =J35*('Допущения'!$C$19+'Допущения'!$D$19) | K40: =K35*('Допущения'!$C$19+'Допущения'!$D$19) | ... AA40: =AA35*('Допущения'!$C$19+'Допущения'!$D$19) | AB40: =SUM(D40:AA40)
A41: C05 | B41: Rental-локеры | C41: VARC | D41: =D36*'Допущения'!$H$19 | E41: =E36*'Допущения'!$H$19 | F41: =F36*'Допущения'!$H$19 | G41: =G36*'Допущения'!$H$19 | H41: =H36*'Допущения'!$H$19 | I41: =I36*'Допущения'!$H$19 | J41: =J36*'Допущения'!$H$19 | K41: =K36*'Допущения'!$H$19 | ... AA41: =AA36*'Допущения'!$H$19 | AB41: =SUM(D41:AA41)
A42: C06 | B42: Локеры для багажа | C42: NEWU | D42: =IF(D$3>='Допущения'!$K$20,D$4*'Допущения'!$J$20*'Допущения'!$I$20,0) | E42: =IF(E$3>='Допущения'!$K$20,E$4*'Допущения'!$J$20*'Допущения'!$I$20,0) | F42: =IF(F$3>='Допущения'!$K$20,F$4*'Допущения'!$J$20*'Допущения'!$I$20,0) | G42: =IF(G$3>='Допущения'!$K$20,G$4*'Допущения'!$J$20*'Допущения'!$I$20,0) | H42: =IF(H$3>='Допущения'!$K$20,H$4*'Допущения'!$J$20*'Допущения'!$I$20,0) | I42: =IF(I$3>='Допущения'!$K$20,I$4*'Допущения'!$J$20*'Допущения'!$I$20,0) | J42: =IF(J$3>='Допущения'!$K$20,J$4*'Допущения'!$J$20*'Допущения'!$I$20,0) | K42: =IF(K$3>='Допущения'!$K$20,K$4*'Допущения'!$J$20*'Допущения'!$I$20,0) | ... AA42: =IF(AA$3>='Допущения'!$K$20,AA$4*'Допущения'!$J$20*'Допущения'!$I$20,0) | AB42: =SUM(D42:AA42)
A43: C06 | B43: Локеры для багажа | C43: ACTU | D43: =D42 | E43: =D43*(1-'Допущения'!$C$6)+E42 | F43: =E43*(1-'Допущения'!$C$6)+F42 | G43: =F43*(1-'Допущения'!$C$6)+G42 | H43: =G43*(1-'Допущения'!$C$6)+H42 | I43: =H43*(1-'Допущения'!$C$6)+I42 | J43: =I43*(1-'Допущения'!$C$6)+J42 | K43: =J43*(1-'Допущения'!$C$6)+K42 | L43: =K43*(1-'Допущения'!$C$6)+L42 | ... AA43: =Z43*(1-'Допущения'!$C$6)+AA42 | AB43: =SUM(D43:AA43)
A44: C06 | B44: Локеры для багажа | C44: HWREV | D44: =D42*'Допущения'!$E$20 | E44: =E42*'Допущения'!$E$20 | F44: =F42*'Допущения'!$E$20 | G44: =G42*'Допущения'!$E$20 | H44: =H42*'Допущения'!$E$20 | I44: =I42*'Допущения'!$E$20 | J44: =J42*'Допущения'!$E$20 | K44: =K42*'Допущения'!$E$20 | ... AA44: =AA42*'Допущения'!$E$20 | AB44: =SUM(D44:AA44)
A45: C06 | B45: Локеры для багажа | C45: RECREV | D45: =D43*'Допущения'!$F$20 | E45: =E43*'Допущения'!$F$20 | F45: =F43*'Допущения'!$F$20 | G45: =G43*'Допущения'!$F$20 | H45: =H43*'Допущения'!$F$20 | I45: =I43*'Допущения'!$F$20 | J45: =J43*'Допущения'!$F$20 | K45: =K43*'Допущения'!$F$20 | ... AA45: =AA43*'Допущения'!$F$20 | AB45: =SUM(D45:AA45)
A46: C06 | B46: Локеры для багажа | C46: TXNREV | D46: =D43*'Допущения'!$G$20 | E46: =E43*'Допущения'!$G$20 | F46: =F43*'Допущения'!$G$20 | G46: =G43*'Допущения'!$G$20 | H46: =H43*'Допущения'!$G$20 | I46: =I43*'Допущения'!$G$20 | J46: =J43*'Допущения'!$G$20 | K46: =K43*'Допущения'!$G$20 | ... AA46: =AA43*'Допущения'!$G$20 | AB46: =SUM(D46:AA46)
A47: C06 | B47: Локеры для багажа | C47: COGS | D47: =D42*('Допущения'!$C$20+'Допущения'!$D$20) | E47: =E42*('Допущения'!$C$20+'Допущения'!$D$20) | F47: =F42*('Допущения'!$C$20+'Допущения'!$D$20) | G47: =G42*('Допущения'!$C$20+'Допущения'!$D$20) | H47: =H42*('Допущения'!$C$20+'Допущения'!$D$20) | I47: =I42*('Допущения'!$C$20+'Допущения'!$D$20) | J47: =J42*('Допущения'!$C$20+'Допущения'!$D$20) | K47: =K42*('Допущения'!$C$20+'Допущения'!$D$20) | ... AA47: =AA42*('Допущения'!$C$20+'Допущения'!$D$20) | AB47: =SUM(D47:AA47)
A48: C06 | B48: Локеры для багажа | C48: VARC | D48: =D43*'Допущения'!$H$20 | E48: =E43*'Допущения'!$H$20 | F48: =F43*'Допущения'!$H$20 | G48: =G43*'Допущения'!$H$20 | H48: =H43*'Допущения'!$H$20 | I48: =I43*'Допущения'!$H$20 | J48: =J43*'Допущения'!$H$20 | K48: =K43*'Допущения'!$H$20 | ... AA48: =AA43*'Допущения'!$H$20 | AB48: =SUM(D48:AA48)
A49: C07 | B49: Аренда power bank | C49: NEWU | D49: =IF(D$3>='Допущения'!$K$21,D$4*'Допущения'!$J$21*'Допущения'!$I$21,0) | E49: =IF(E$3>='Допущения'!$K$21,E$4*'Допущения'!$J$21*'Допущения'!$I$21,0) | F49: =IF(F$3>='Допущения'!$K$21,F$4*'Допущения'!$J$21*'Допущения'!$I$21,0) | G49: =IF(G$3>='Допущения'!$K$21,G$4*'Допущения'!$J$21*'Допущения'!$I$21,0) | H49: =IF(H$3>='Допущения'!$K$21,H$4*'Допущения'!$J$21*'Допущения'!$I$21,0) | I49: =IF(I$3>='Допущения'!$K$21,I$4*'Допущения'!$J$21*'Допущения'!$I$21,0) | J49: =IF(J$3>='Допущения'!$K$21,J$4*'Допущения'!$J$21*'Допущения'!$I$21,0) | K49: =IF(K$3>='Допущения'!$K$21,K$4*'Допущения'!$J$21*'Допущения'!$I$21,0) | ... AA49: =IF(AA$3>='Допущения'!$K$21,AA$4*'Допущения'!$J$21*'Допущения'!$I$21,0) | AB49: =SUM(D49:AA49)
A50: C07 | B50: Аренда power bank | C50: ACTU | D50: =D49 | E50: =D50*(1-'Допущения'!$C$6)+E49 | F50: =E50*(1-'Допущения'!$C$6)+F49 | G50: =F50*(1-'Допущения'!$C$6)+G49 | H50: =G50*(1-'Допущения'!$C$6)+H49 | I50: =H50*(1-'Допущения'!$C$6)+I49 | J50: =I50*(1-'Допущения'!$C$6)+J49 | K50: =J50*(1-'Допущения'!$C$6)+K49 | L50: =K50*(1-'Допущения'!$C$6)+L49 | ... AA50: =Z50*(1-'Допущения'!$C$6)+AA49 | AB50: =SUM(D50:AA50)
A51: C07 | B51: Аренда power bank | C51: HWREV | D51: =D49*'Допущения'!$E$21 | E51: =E49*'Допущения'!$E$21 | F51: =F49*'Допущения'!$E$21 | G51: =G49*'Допущения'!$E$21 | H51: =H49*'Допущения'!$E$21 | I51: =I49*'Допущения'!$E$21 | J51: =J49*'Допущения'!$E$21 | K51: =K49*'Допущения'!$E$21 | ... AA51: =AA49*'Допущения'!$E$21 | AB51: =SUM(D51:AA51)
A52: C07 | B52: Аренда power bank | C52: RECREV | D52: =D50*'Допущения'!$F$21 | E52: =E50*'Допущения'!$F$21 | F52: =F50*'Допущения'!$F$21 | G52: =G50*'Допущения'!$F$21 | H52: =H50*'Допущения'!$F$21 | I52: =I50*'Допущения'!$F$21 | J52: =J50*'Допущения'!$F$21 | K52: =K50*'Допущения'!$F$21 | ... AA52: =AA50*'Допущения'!$F$21 | AB52: =SUM(D52:AA52)
A53: C07 | B53: Аренда power bank | C53: TXNREV | D53: =D50*'Допущения'!$G$21 | E53: =E50*'Допущения'!$G$21 | F53: =F50*'Допущения'!$G$21 | G53: =G50*'Допущения'!$G$21 | H53: =H50*'Допущения'!$G$21 | I53: =I50*'Допущения'!$G$21 | J53: =J50*'Допущения'!$G$21 | K53: =K50*'Допущения'!$G$21 | ... AA53: =AA50*'Допущения'!$G$21 | AB53: =SUM(D53:AA53)
A54: C07 | B54: Аренда power bank | C54: COGS | D54: =D49*('Допущения'!$C$21+'Допущения'!$D$21) | E54: =E49*('Допущения'!$C$21+'Допущения'!$D$21) | F54: =F49*('Допущения'!$C$21+'Допущения'!$D$21) | G54: =G49*('Допущения'!$C$21+'Допущения'!$D$21) | H54: =H49*('Допущения'!$C$21+'Допущения'!$D$21) | I54: =I49*('Допущения'!$C$21+'Допущения'!$D$21) | J54: =J49*('Допущения'!$C$21+'Допущения'!$D$21) | K54: =K49*('Допущения'!$C$21+'Допущения'!$D$21) | ... AA54: =AA49*('Допущения'!$C$21+'Допущения'!$D$21) | AB54: =SUM(D54:AA54)
A55: C07 | B55: Аренда power bank | C55: VARC | D55: =D50*'Допущения'!$H$21 | E55: =E50*'Допущения'!$H$21 | F55: =F50*'Допущения'!$H$21 | G55: =G50*'Допущения'!$H$21 | H55: =H50*'Допущения'!$H$21 | I55: =I50*'Допущения'!$H$21 | J55: =J50*'Допущения'!$H$21 | K55: =K50*'Допущения'!$H$21 | ... AA55: =AA50*'Допущения'!$H$21 | AB55: =SUM(D55:AA55)
A56: C08 | B56: IoT-комплект энергосбережения (на номер) | C56: NEWU | D56: =IF(D$3>='Допущения'!$K$22,D$4*'Допущения'!$J$22*'Допущения'!$I$22,0) | E56: =IF(E$3>='Допущения'!$K$22,E$4*'Допущения'!$J$22*'Допущения'!$I$22,0) | F56: =IF(F$3>='Допущения'!$K$22,F$4*'Допущения'!$J$22*'Допущения'!$I$22,0) | G56: =IF(G$3>='Допущения'!$K$22,G$4*'Допущения'!$J$22*'Допущения'!$I$22,0) | H56: =IF(H$3>='Допущения'!$K$22,H$4*'Допущения'!$J$22*'Допущения'!$I$22,0) | I56: =IF(I$3>='Допущения'!$K$22,I$4*'Допущения'!$J$22*'Допущения'!$I$22,0) | J56: =IF(J$3>='Допущения'!$K$22,J$4*'Допущения'!$J$22*'Допущения'!$I$22,0) | K56: =IF(K$3>='Допущения'!$K$22,K$4*'Допущения'!$J$22*'Допущения'!$I$22,0) | ... AA56: =IF(AA$3>='Допущения'!$K$22,AA$4*'Допущения'!$J$22*'Допущения'!$I$22,0) | AB56: =SUM(D56:AA56)
A57: C08 | B57: IoT-комплект энергосбережения (на номер) | C57: ACTU | D57: =D56 | E57: =D57*(1-'Допущения'!$C$6)+E56 | F57: =E57*(1-'Допущения'!$C$6)+F56 | G57: =F57*(1-'Допущения'!$C$6)+G56 | H57: =G57*(1-'Допущения'!$C$6)+H56 | I57: =H57*(1-'Допущения'!$C$6)+I56 | J57: =I57*(1-'Допущения'!$C$6)+J56 | K57: =J57*(1-'Допущения'!$C$6)+K56 | L57: =K57*(1-'Допущения'!$C$6)+L56 | ... AA57: =Z57*(1-'Допущения'!$C$6)+AA56 | AB57: =SUM(D57:AA57)
A58: C08 | B58: IoT-комплект энергосбережения (на номер) | C58: HWREV | D58: =D56*'Допущения'!$E$22 | E58: =E56*'Допущения'!$E$22 | F58: =F56*'Допущения'!$E$22 | G58: =G56*'Допущения'!$E$22 | H58: =H56*'Допущения'!$E$22 | I58: =I56*'Допущения'!$E$22 | J58: =J56*'Допущения'!$E$22 | K58: =K56*'Допущения'!$E$22 | ... AA58: =AA56*'Допущения'!$E$22 | AB58: =SUM(D58:AA58)
A59: C08 | B59: IoT-комплект энергосбережения (на номер) | C59: RECREV | D59: =D57*'Допущения'!$F$22 | E59: =E57*'Допущения'!$F$22 | F59: =F57*'Допущения'!$F$22 | G59: =G57*'Допущения'!$F$22 | H59: =H57*'Допущения'!$F$22 | I59: =I57*'Допущения'!$F$22 | J59: =J57*'Допущения'!$F$22 | K59: =K57*'Допущения'!$F$22 | ... AA59: =AA57*'Допущения'!$F$22 | AB59: =SUM(D59:AA59)
A60: C08 | B60: IoT-комплект энергосбережения (на номер) | C60: TXNREV | D60: =D57*'Допущения'!$G$22 | E60: =E57*'Допущения'!$G$22 | F60: =F57*'Допущения'!$G$22 | G60: =G57*'Допущения'!$G$22 | H60: =H57*'Допущения'!$G$22 | I60: =I57*'Допущения'!$G$22 | J60: =J57*'Допущения'!$G$22 | K60: =K57*'Допущения'!$G$22 | ... AA60: =AA57*'Допущения'!$G$22 | AB60: =SUM(D60:AA60)
A61: C08 | B61: IoT-комплект энергосбережения (на номер) | C61: COGS | D61: =D56*('Допущения'!$C$22+'Допущения'!$D$22) | E61: =E56*('Допущения'!$C$22+'Допущения'!$D$22) | F61: =F56*('Допущения'!$C$22+'Допущения'!$D$22) | G61: =G56*('Допущения'!$C$22+'Допущения'!$D$22) | H61: =H56*('Допущения'!$C$22+'Допущения'!$D$22) | I61: =I56*('Допущения'!$C$22+'Допущения'!$D$22) | J61: =J56*('Допущения'!$C$22+'Допущения'!$D$22) | K61: =K56*('Допущения'!$C$22+'Допущения'!$D$22) | ... AA61: =AA56*('Допущения'!$C$22+'Допущения'!$D$22) | AB61: =SUM(D61:AA61)
A62: C08 | B62: IoT-комплект энергосбережения (на номер) | C62: VARC | D62: =D57*'Допущения'!$H$22 | E62: =E57*'Допущения'!$H$22 | F62: =F57*'Допущения'!$H$22 | G62: =G57*'Допущения'!$H$22 | H62: =H57*'Допущения'!$H$22 | I62: =I57*'Допущения'!$H$22 | J62: =J57*'Допущения'!$H$22 | K62: =K57*'Допущения'!$H$22 | ... AA62: =AA57*'Допущения'!$H$22 | AB62: =SUM(D62:AA62)
A63: C09 | B63: Smart access (на дверь) | C63: NEWU | D63: =IF(D$3>='Допущения'!$K$23,D$4*'Допущения'!$J$23*'Допущения'!$I$23,0) | E63: =IF(E$3>='Допущения'!$K$23,E$4*'Допущения'!$J$23*'Допущения'!$I$23,0) | F63: =IF(F$3>='Допущения'!$K$23,F$4*'Допущения'!$J$23*'Допущения'!$I$23,0) | G63: =IF(G$3>='Допущения'!$K$23,G$4*'Допущения'!$J$23*'Допущения'!$I$23,0) | H63: =IF(H$3>='Допущения'!$K$23,H$4*'Допущения'!$J$23*'Допущения'!$I$23,0) | I63: =IF(I$3>='Допущения'!$K$23,I$4*'Допущения'!$J$23*'Допущения'!$I$23,0) | J63: =IF(J$3>='Допущения'!$K$23,J$4*'Допущения'!$J$23*'Допущения'!$I$23,0) | K63: =IF(K$3>='Допущения'!$K$23,K$4*'Допущения'!$J$23*'Допущения'!$I$23,0) | ... AA63: =IF(AA$3>='Допущения'!$K$23,AA$4*'Допущения'!$J$23*'Допущения'!$I$23,0) | AB63: =SUM(D63:AA63)
A64: C09 | B64: Smart access (на дверь) | C64: ACTU | D64: =D63 | E64: =D64*(1-'Допущения'!$C$6)+E63 | F64: =E64*(1-'Допущения'!$C$6)+F63 | G64: =F64*(1-'Допущения'!$C$6)+G63 | H64: =G64*(1-'Допущения'!$C$6)+H63 | I64: =H64*(1-'Допущения'!$C$6)+I63 | J64: =I64*(1-'Допущения'!$C$6)+J63 | K64: =J64*(1-'Допущения'!$C$6)+K63 | L64: =K64*(1-'Допущения'!$C$6)+L63 | ... AA64: =Z64*(1-'Допущения'!$C$6)+AA63 | AB64: =SUM(D64:AA64)
A65: C09 | B65: Smart access (на дверь) | C65: HWREV | D65: =D63*'Допущения'!$E$23 | E65: =E63*'Допущения'!$E$23 | F65: =F63*'Допущения'!$E$23 | G65: =G63*'Допущения'!$E$23 | H65: =H63*'Допущения'!$E$23 | I65: =I63*'Допущения'!$E$23 | J65: =J63*'Допущения'!$E$23 | K65: =K63*'Допущения'!$E$23 | ... AA65: =AA63*'Допущения'!$E$23 | AB65: =SUM(D65:AA65)
A66: C09 | B66: Smart access (на дверь) | C66: RECREV | D66: =D64*'Допущения'!$F$23 | E66: =E64*'Допущения'!$F$23 | F66: =F64*'Допущения'!$F$23 | G66: =G64*'Допущения'!$F$23 | H66: =H64*'Допущения'!$F$23 | I66: =I64*'Допущения'!$F$23 | J66: =J64*'Допущения'!$F$23 | K66: =K64*'Допущения'!$F$23 | ... AA66: =AA64*'Допущения'!$F$23 | AB66: =SUM(D66:AA66)
A67: C09 | B67: Smart access (на дверь) | C67: TXNREV | D67: =D64*'Допущения'!$G$23 | E67: =E64*'Допущения'!$G$23 | F67: =F64*'Допущения'!$G$23 | G67: =G64*'Допущения'!$G$23 | H67: =H64*'Допущения'!$G$23 | I67: =I64*'Допущения'!$G$23 | J67: =J64*'Допущения'!$G$23 | K67: =K64*'Допущения'!$G$23 | ... AA67: =AA64*'Допущения'!$G$23 | AB67: =SUM(D67:AA67)
A68: C09 | B68: Smart access (на дверь) | C68: COGS | D68: =D63*('Допущения'!$C$23+'Допущения'!$D$23) | E68: =E63*('Допущения'!$C$23+'Допущения'!$D$23) | F68: =F63*('Допущения'!$C$23+'Допущения'!$D$23) | G68: =G63*('Допущения'!$C$23+'Допущения'!$D$23) | H68: =H63*('Допущения'!$C$23+'Допущения'!$D$23) | I68: =I63*('Допущения'!$C$23+'Допущения'!$D$23) | J68: =J63*('Допущения'!$C$23+'Допущения'!$D$23) | K68: =K63*('Допущения'!$C$23+'Допущения'!$D$23) | ... AA68: =AA63*('Допущения'!$C$23+'Допущения'!$D$23) | AB68: =SUM(D68:AA68)
A69: C09 | B69: Smart access (на дверь) | C69: VARC | D69: =D64*'Допущения'!$H$23 | E69: =E64*'Допущения'!$H$23 | F69: =F64*'Допущения'!$H$23 | G69: =G64*'Допущения'!$H$23 | H69: =H64*'Допущения'!$H$23 | I69: =I64*'Допущения'!$H$23 | J69: =J64*'Допущения'!$H$23 | K69: =K64*'Допущения'!$H$23 | ... AA69: =AA64*'Допущения'!$H$23 | AB69: =SUM(D69:AA69)
A70: C10 | B70: Датчики Healthy Room (на номер) | C70: NEWU | D70: =IF(D$3>='Допущения'!$K$24,D$4*'Допущения'!$J$24*'Допущения'!$I$24,0) | E70: =IF(E$3>='Допущения'!$K$24,E$4*'Допущения'!$J$24*'Допущения'!$I$24,0) | F70: =IF(F$3>='Допущения'!$K$24,F$4*'Допущения'!$J$24*'Допущения'!$I$24,0) | G70: =IF(G$3>='Допущения'!$K$24,G$4*'Допущения'!$J$24*'Допущения'!$I$24,0) | H70: =IF(H$3>='Допущения'!$K$24,H$4*'Допущения'!$J$24*'Допущения'!$I$24,0) | I70: =IF(I$3>='Допущения'!$K$24,I$4*'Допущения'!$J$24*'Допущения'!$I$24,0) | J70: =IF(J$3>='Допущения'!$K$24,J$4*'Допущения'!$J$24*'Допущения'!$I$24,0) | K70: =IF(K$3>='Допущения'!$K$24,K$4*'Допущения'!$J$24*'Допущения'!$I$24,0) | ... AA70: =IF(AA$3>='Допущения'!$K$24,AA$4*'Допущения'!$J$24*'Допущения'!$I$24,0) | AB70: =SUM(D70:AA70)
A71: C10 | B71: Датчики Healthy Room (на номер) | C71: ACTU | D71: =D70 | E71: =D71*(1-'Допущения'!$C$6)+E70 | F71: =E71*(1-'Допущения'!$C$6)+F70 | G71: =F71*(1-'Допущения'!$C$6)+G70 | H71: =G71*(1-'Допущения'!$C$6)+H70 | I71: =H71*(1-'Допущения'!$C$6)+I70 | J71: =I71*(1-'Допущения'!$C$6)+J70 | K71: =J71*(1-'Допущения'!$C$6)+K70 | L71: =K71*(1-'Допущения'!$C$6)+L70 | ... AA71: =Z71*(1-'Допущения'!$C$6)+AA70 | AB71: =SUM(D71:AA71)
A72: C10 | B72: Датчики Healthy Room (на номер) | C72: HWREV | D72: =D70*'Допущения'!$E$24 | E72: =E70*'Допущения'!$E$24 | F72: =F70*'Допущения'!$E$24 | G72: =G70*'Допущения'!$E$24 | H72: =H70*'Допущения'!$E$24 | I72: =I70*'Допущения'!$E$24 | J72: =J70*'Допущения'!$E$24 | K72: =K70*'Допущения'!$E$24 | ... AA72: =AA70*'Допущения'!$E$24 | AB72: =SUM(D72:AA72)
A73: C10 | B73: Датчики Healthy Room (на номер) | C73: RECREV | D73: =D71*'Допущения'!$F$24 | E73: =E71*'Допущения'!$F$24 | F73: =F71*'Допущения'!$F$24 | G73: =G71*'Допущения'!$F$24 | H73: =H71*'Допущения'!$F$24 | I73: =I71*'Допущения'!$F$24 | J73: =J71*'Допущения'!$F$24 | K73: =K71*'Допущения'!$F$24 | ... AA73: =AA71*'Допущения'!$F$24 | AB73: =SUM(D73:AA73)
A74: C10 | B74: Датчики Healthy Room (на номер) | C74: TXNREV | D74: =D71*'Допущения'!$G$24 | E74: =E71*'Допущения'!$G$24 | F74: =F71*'Допущения'!$G$24 | G74: =G71*'Допущения'!$G$24 | H74: =H71*'Допущения'!$G$24 | I74: =I71*'Допущения'!$G$24 | J74: =J71*'Допущения'!$G$24 | K74: =K71*'Допущения'!$G$24 | ... AA74: =AA71*'Допущения'!$G$24 | AB74: =SUM(D74:AA74)
A75: C10 | B75: Датчики Healthy Room (на номер) | C75: COGS | D75: =D70*('Допущения'!$C$24+'Допущения'!$D$24) | E75: =E70*('Допущения'!$C$24+'Допущения'!$D$24) | F75: =F70*('Допущения'!$C$24+'Допущения'!$D$24) | G75: =G70*('Допущения'!$C$24+'Допущения'!$D$24) | H75: =H70*('Допущения'!$C$24+'Допущения'!$D$24) | I75: =I70*('Допущения'!$C$24+'Допущения'!$D$24) | J75: =J70*('Допущения'!$C$24+'Допущения'!$D$24) | K75: =K70*('Допущения'!$C$24+'Допущения'!$D$24) | ... AA75: =AA70*('Допущения'!$C$24+'Допущения'!$D$24) | AB75: =SUM(D75:AA75)
A76: C10 | B76: Датчики Healthy Room (на номер) | C76: VARC | D76: =D71*'Допущения'!$H$24 | E76: =E71*'Допущения'!$H$24 | F76: =F71*'Допущения'!$H$24 | G76: =G71*'Допущения'!$H$24 | H76: =H71*'Допущения'!$H$24 | I76: =I71*'Допущения'!$H$24 | J76: =J71*'Допущения'!$H$24 | K76: =K71*'Допущения'!$H$24 | ... AA76: =AA71*'Допущения'!$H$24 | AB76: =SUM(D76:AA76)
A77: C11 | B77: Киоск check-in / ID | C77: NEWU | D77: =IF(D$3>='Допущения'!$K$25,D$4*'Допущения'!$J$25*'Допущения'!$I$25,0) | E77: =IF(E$3>='Допущения'!$K$25,E$4*'Допущения'!$J$25*'Допущения'!$I$25,0) | F77: =IF(F$3>='Допущения'!$K$25,F$4*'Допущения'!$J$25*'Допущения'!$I$25,0) | G77: =IF(G$3>='Допущения'!$K$25,G$4*'Допущения'!$J$25*'Допущения'!$I$25,0) | H77: =IF(H$3>='Допущения'!$K$25,H$4*'Допущения'!$J$25*'Допущения'!$I$25,0) | I77: =IF(I$3>='Допущения'!$K$25,I$4*'Допущения'!$J$25*'Допущения'!$I$25,0) | J77: =IF(J$3>='Допущения'!$K$25,J$4*'Допущения'!$J$25*'Допущения'!$I$25,0) | K77: =IF(K$3>='Допущения'!$K$25,K$4*'Допущения'!$J$25*'Допущения'!$I$25,0) | ... AA77: =IF(AA$3>='Допущения'!$K$25,AA$4*'Допущения'!$J$25*'Допущения'!$I$25,0) | AB77: =SUM(D77:AA77)
A78: C11 | B78: Киоск check-in / ID | C78: ACTU | D78: =D77 | E78: =D78*(1-'Допущения'!$C$6)+E77 | F78: =E78*(1-'Допущения'!$C$6)+F77 | G78: =F78*(1-'Допущения'!$C$6)+G77 | H78: =G78*(1-'Допущения'!$C$6)+H77 | I78: =H78*(1-'Допущения'!$C$6)+I77 | J78: =I78*(1-'Допущения'!$C$6)+J77 | K78: =J78*(1-'Допущения'!$C$6)+K77 | L78: =K78*(1-'Допущения'!$C$6)+L77 | ... AA78: =Z78*(1-'Допущения'!$C$6)+AA77 | AB78: =SUM(D78:AA78)
A79: C11 | B79: Киоск check-in / ID | C79: HWREV | D79: =D77*'Допущения'!$E$25 | E79: =E77*'Допущения'!$E$25 | F79: =F77*'Допущения'!$E$25 | G79: =G77*'Допущения'!$E$25 | H79: =H77*'Допущения'!$E$25 | I79: =I77*'Допущения'!$E$25 | J79: =J77*'Допущения'!$E$25 | K79: =K77*'Допущения'!$E$25 | ... AA79: =AA77*'Допущения'!$E$25 | AB79: =SUM(D79:AA79)
A80: C11 | B80: Киоск check-in / ID | C80: RECREV | D80: =D78*'Допущения'!$F$25 | E80: =E78*'Допущения'!$F$25 | F80: =F78*'Допущения'!$F$25 | G80: =G78*'Допущения'!$F$25 | H80: =H78*'Допущения'!$F$25 | I80: =I78*'Допущения'!$F$25 | J80: =J78*'Допущения'!$F$25 | K80: =K78*'Допущения'!$F$25 | ... AA80: =AA78*'Допущения'!$F$25 | AB80: =SUM(D80:AA80)
A81: C11 | B81: Киоск check-in / ID | C81: TXNREV | D81: =D78*'Допущения'!$G$25 | E81: =E78*'Допущения'!$G$25 | F81: =F78*'Допущения'!$G$25 | G81: =G78*'Допущения'!$G$25 | H81: =H78*'Допущения'!$G$25 | I81: =I78*'Допущения'!$G$25 | J81: =J78*'Допущения'!$G$25 | K81: =K78*'Допущения'!$G$25 | ... AA81: =AA78*'Допущения'!$G$25 | AB81: =SUM(D81:AA81)
A82: C11 | B82: Киоск check-in / ID | C82: COGS | D82: =D77*('Допущения'!$C$25+'Допущения'!$D$25) | E82: =E77*('Допущения'!$C$25+'Допущения'!$D$25) | F82: =F77*('Допущения'!$C$25+'Допущения'!$D$25) | G82: =G77*('Допущения'!$C$25+'Допущения'!$D$25) | H82: =H77*('Допущения'!$C$25+'Допущения'!$D$25) | I82: =I77*('Допущения'!$C$25+'Допущения'!$D$25) | J82: =J77*('Допущения'!$C$25+'Допущения'!$D$25) | K82: =K77*('Допущения'!$C$25+'Допущения'!$D$25) | ... AA82: =AA77*('Допущения'!$C$25+'Допущения'!$D$25) | AB82: =SUM(D82:AA82)
A83: C11 | B83: Киоск check-in / ID | C83: VARC | D83: =D78*'Допущения'!$H$25 | E83: =E78*'Допущения'!$H$25 | F83: =F78*'Допущения'!$H$25 | G83: =G78*'Допущения'!$H$25 | H83: =H78*'Допущения'!$H$25 | I83: =I78*'Допущения'!$H$25 | J83: =J78*'Допущения'!$H$25 | K83: =K78*'Допущения'!$H$25 | ... AA83: =AA78*'Допущения'!$H$25 | AB83: =SUM(D83:AA83)
A84: C12 | B84: Локальный marketplace | C84: NEWU | D84: =IF(D$3>='Допущения'!$K$26,D$4*'Допущения'!$J$26*'Допущения'!$I$26,0) | E84: =IF(E$3>='Допущения'!$K$26,E$4*'Допущения'!$J$26*'Допущения'!$I$26,0) | F84: =IF(F$3>='Допущения'!$K$26,F$4*'Допущения'!$J$26*'Допущения'!$I$26,0) | G84: =IF(G$3>='Допущения'!$K$26,G$4*'Допущения'!$J$26*'Допущения'!$I$26,0) | H84: =IF(H$3>='Допущения'!$K$26,H$4*'Допущения'!$J$26*'Допущения'!$I$26,0) | I84: =IF(I$3>='Допущения'!$K$26,I$4*'Допущения'!$J$26*'Допущения'!$I$26,0) | J84: =IF(J$3>='Допущения'!$K$26,J$4*'Допущения'!$J$26*'Допущения'!$I$26,0) | K84: =IF(K$3>='Допущения'!$K$26,K$4*'Допущения'!$J$26*'Допущения'!$I$26,0) | ... AA84: =IF(AA$3>='Допущения'!$K$26,AA$4*'Допущения'!$J$26*'Допущения'!$I$26,0) | AB84: =SUM(D84:AA84)
A85: C12 | B85: Локальный marketplace | C85: ACTU | D85: =D84 | E85: =D85*(1-'Допущения'!$C$6)+E84 | F85: =E85*(1-'Допущения'!$C$6)+F84 | G85: =F85*(1-'Допущения'!$C$6)+G84 | H85: =G85*(1-'Допущения'!$C$6)+H84 | I85: =H85*(1-'Допущения'!$C$6)+I84 | J85: =I85*(1-'Допущения'!$C$6)+J84 | K85: =J85*(1-'Допущения'!$C$6)+K84 | L85: =K85*(1-'Допущения'!$C$6)+L84 | ... AA85: =Z85*(1-'Допущения'!$C$6)+AA84 | AB85: =SUM(D85:AA85)
A86: C12 | B86: Локальный marketplace | C86: HWREV | D86: =D84*'Допущения'!$E$26 | E86: =E84*'Допущения'!$E$26 | F86: =F84*'Допущения'!$E$26 | G86: =G84*'Допущения'!$E$26 | H86: =H84*'Допущения'!$E$26 | I86: =I84*'Допущения'!$E$26 | J86: =J84*'Допущения'!$E$26 | K86: =K84*'Допущения'!$E$26 | ... AA86: =AA84*'Допущения'!$E$26 | AB86: =SUM(D86:AA86)
A87: C12 | B87: Локальный marketplace | C87: RECREV | D87: =D85*'Допущения'!$F$26 | E87: =E85*'Допущения'!$F$26 | F87: =F85*'Допущения'!$F$26 | G87: =G85*'Допущения'!$F$26 | H87: =H85*'Допущения'!$F$26 | I87: =I85*'Допущения'!$F$26 | J87: =J85*'Допущения'!$F$26 | K87: =K85*'Допущения'!$F$26 | ... AA87: =AA85*'Допущения'!$F$26 | AB87: =SUM(D87:AA87)
A88: C12 | B88: Локальный marketplace | C88: TXNREV | D88: =D85*'Допущения'!$G$26 | E88: =E85*'Допущения'!$G$26 | F88: =F85*'Допущения'!$G$26 | G88: =G85*'Допущения'!$G$26 | H88: =H85*'Допущения'!$G$26 | I88: =I85*'Допущения'!$G$26 | J88: =J85*'Допущения'!$G$26 | K88: =K85*'Допущения'!$G$26 | ... AA88: =AA85*'Допущения'!$G$26 | AB88: =SUM(D88:AA88)
A89: C12 | B89: Локальный marketplace | C89: COGS | D89: =D84*('Допущения'!$C$26+'Допущения'!$D$26) | E89: =E84*('Допущения'!$C$26+'Допущения'!$D$26) | F89: =F84*('Допущения'!$C$26+'Допущения'!$D$26) | G89: =G84*('Допущения'!$C$26+'Допущения'!$D$26) | H89: =H84*('Допущения'!$C$26+'Допущения'!$D$26) | I89: =I84*('Допущения'!$C$26+'Допущения'!$D$26) | J89: =J84*('Допущения'!$C$26+'Допущения'!$D$26) | K89: =K84*('Допущения'!$C$26+'Допущения'!$D$26) | ... AA89: =AA84*('Допущения'!$C$26+'Допущения'!$D$26) | AB89: =SUM(D89:AA89)
A90: C12 | B90: Локальный marketplace | C90: VARC | D90: =D85*'Допущения'!$H$26 | E90: =E85*'Допущения'!$H$26 | F90: =F85*'Допущения'!$H$26 | G90: =G85*'Допущения'!$H$26 | H90: =H85*'Допущения'!$H$26 | I90: =I85*'Допущения'!$H$26 | J90: =J85*'Допущения'!$H$26 | K90: =K85*'Допущения'!$H$26 | ... AA90: =AA85*'Допущения'!$H$26 | AB90: =SUM(D90:AA90)
A91: C13 | B91: Робот-доставщик (аренда) | C91: NEWU | D91: =IF(D$3>='Допущения'!$K$27,D$4*'Допущения'!$J$27*'Допущения'!$I$27,0) | E91: =IF(E$3>='Допущения'!$K$27,E$4*'Допущения'!$J$27*'Допущения'!$I$27,0) | F91: =IF(F$3>='Допущения'!$K$27,F$4*'Допущения'!$J$27*'Допущения'!$I$27,0) | G91: =IF(G$3>='Допущения'!$K$27,G$4*'Допущения'!$J$27*'Допущения'!$I$27,0) | H91: =IF(H$3>='Допущения'!$K$27,H$4*'Допущения'!$J$27*'Допущения'!$I$27,0) | I91: =IF(I$3>='Допущения'!$K$27,I$4*'Допущения'!$J$27*'Допущения'!$I$27,0) | J91: =IF(J$3>='Допущения'!$K$27,J$4*'Допущения'!$J$27*'Допущения'!$I$27,0) | K91: =IF(K$3>='Допущения'!$K$27,K$4*'Допущения'!$J$27*'Допущения'!$I$27,0) | ... AA91: =IF(AA$3>='Допущения'!$K$27,AA$4*'Допущения'!$J$27*'Допущения'!$I$27,0) | AB91: =SUM(D91:AA91)
A92: C13 | B92: Робот-доставщик (аренда) | C92: ACTU | D92: =D91 | E92: =D92*(1-'Допущения'!$C$6)+E91 | F92: =E92*(1-'Допущения'!$C$6)+F91 | G92: =F92*(1-'Допущения'!$C$6)+G91 | H92: =G92*(1-'Допущения'!$C$6)+H91 | I92: =H92*(1-'Допущения'!$C$6)+I91 | J92: =I92*(1-'Допущения'!$C$6)+J91 | K92: =J92*(1-'Допущения'!$C$6)+K91 | L92: =K92*(1-'Допущения'!$C$6)+L91 | ... AA92: =Z92*(1-'Допущения'!$C$6)+AA91 | AB92: =SUM(D92:AA92)
A93: C13 | B93: Робот-доставщик (аренда) | C93: HWREV | D93: =D91*'Допущения'!$E$27 | E93: =E91*'Допущения'!$E$27 | F93: =F91*'Допущения'!$E$27 | G93: =G91*'Допущения'!$E$27 | H93: =H91*'Допущения'!$E$27 | I93: =I91*'Допущения'!$E$27 | J93: =J91*'Допущения'!$E$27 | K93: =K91*'Допущения'!$E$27 | ... AA93: =AA91*'Допущения'!$E$27 | AB93: =SUM(D93:AA93)
A94: C13 | B94: Робот-доставщик (аренда) | C94: RECREV | D94: =D92*'Допущения'!$F$27 | E94: =E92*'Допущения'!$F$27 | F94: =F92*'Допущения'!$F$27 | G94: =G92*'Допущения'!$F$27 | H94: =H92*'Допущения'!$F$27 | I94: =I92*'Допущения'!$F$27 | J94: =J92*'Допущения'!$F$27 | K94: =K92*'Допущения'!$F$27 | ... AA94: =AA92*'Допущения'!$F$27 | AB94: =SUM(D94:AA94)
A95: C13 | B95: Робот-доставщик (аренда) | C95: TXNREV | D95: =D92*'Допущения'!$G$27 | E95: =E92*'Допущения'!$G$27 | F95: =F92*'Допущения'!$G$27 | G95: =G92*'Допущения'!$G$27 | H95: =H92*'Допущения'!$G$27 | I95: =I92*'Допущения'!$G$27 | J95: =J92*'Допущения'!$G$27 | K95: =K92*'Допущения'!$G$27 | ... AA95: =AA92*'Допущения'!$G$27 | AB95: =SUM(D95:AA95)
A96: C13 | B96: Робот-доставщик (аренда) | C96: COGS | D96: =D91*('Допущения'!$C$27+'Допущения'!$D$27) | E96: =E91*('Допущения'!$C$27+'Допущения'!$D$27) | F96: =F91*('Допущения'!$C$27+'Допущения'!$D$27) | G96: =G91*('Допущения'!$C$27+'Допущения'!$D$27) | H96: =H91*('Допущения'!$C$27+'Допущения'!$D$27) | I96: =I91*('Допущения'!$C$27+'Допущения'!$D$27) | J96: =J91*('Допущения'!$C$27+'Допущения'!$D$27) | K96: =K91*('Допущения'!$C$27+'Допущения'!$D$27) | ... AA96: =AA91*('Допущения'!$C$27+'Допущения'!$D$27) | AB96: =SUM(D96:AA96)
A97: C13 | B97: Робот-доставщик (аренда) | C97: VARC | D97: =D92*'Допущения'!$H$27 | E97: =E92*'Допущения'!$H$27 | F97: =F92*'Допущения'!$H$27 | G97: =G92*'Допущения'!$H$27 | H97: =H92*'Допущения'!$H$27 | I97: =I92*'Допущения'!$H$27 | J97: =J92*'Допущения'!$H$27 | K97: =K92*'Допущения'!$H$27 | ... AA97: =AA92*'Допущения'!$H$27 | AB97: =SUM(D97:AA97)
A98: C14 | B98: Робот-уборщик (аренда) | C98: NEWU | D98: =IF(D$3>='Допущения'!$K$28,D$4*'Допущения'!$J$28*'Допущения'!$I$28,0) | E98: =IF(E$3>='Допущения'!$K$28,E$4*'Допущения'!$J$28*'Допущения'!$I$28,0) | F98: =IF(F$3>='Допущения'!$K$28,F$4*'Допущения'!$J$28*'Допущения'!$I$28,0) | G98: =IF(G$3>='Допущения'!$K$28,G$4*'Допущения'!$J$28*'Допущения'!$I$28,0) | H98: =IF(H$3>='Допущения'!$K$28,H$4*'Допущения'!$J$28*'Допущения'!$I$28,0) | I98: =IF(I$3>='Допущения'!$K$28,I$4*'Допущения'!$J$28*'Допущения'!$I$28,0) | J98: =IF(J$3>='Допущения'!$K$28,J$4*'Допущения'!$J$28*'Допущения'!$I$28,0) | K98: =IF(K$3>='Допущения'!$K$28,K$4*'Допущения'!$J$28*'Допущения'!$I$28,0) | ... AA98: =IF(AA$3>='Допущения'!$K$28,AA$4*'Допущения'!$J$28*'Допущения'!$I$28,0) | AB98: =SUM(D98:AA98)
A99: C14 | B99: Робот-уборщик (аренда) | C99: ACTU | D99: =D98 | E99: =D99*(1-'Допущения'!$C$6)+E98 | F99: =E99*(1-'Допущения'!$C$6)+F98 | G99: =F99*(1-'Допущения'!$C$6)+G98 | H99: =G99*(1-'Допущения'!$C$6)+H98 | I99: =H99*(1-'Допущения'!$C$6)+I98 | J99: =I99*(1-'Допущения'!$C$6)+J98 | K99: =J99*(1-'Допущения'!$C$6)+K98 | L99: =K99*(1-'Допущения'!$C$6)+L98 | ... AA99: =Z99*(1-'Допущения'!$C$6)+AA98 | AB99: =SUM(D99:AA99)
A100: C14 | B100: Робот-уборщик (аренда) | C100: HWREV | D100: =D98*'Допущения'!$E$28 | E100: =E98*'Допущения'!$E$28 | F100: =F98*'Допущения'!$E$28 | G100: =G98*'Допущения'!$E$28 | H100: =H98*'Допущения'!$E$28 | I100: =I98*'Допущения'!$E$28 | J100: =J98*'Допущения'!$E$28 | K100: =K98*'Допущения'!$E$28 | ... AA100: =AA98*'Допущения'!$E$28 | AB100: =SUM(D100:AA100)
A101: C14 | B101: Робот-уборщик (аренда) | C101: RECREV | D101: =D99*'Допущения'!$F$28 | E101: =E99*'Допущения'!$F$28 | F101: =F99*'Допущения'!$F$28 | G101: =G99*'Допущения'!$F$28 | H101: =H99*'Допущения'!$F$28 | I101: =I99*'Допущения'!$F$28 | J101: =J99*'Допущения'!$F$28 | K101: =K99*'Допущения'!$F$28 | ... AA101: =AA99*'Допущения'!$F$28 | AB101: =SUM(D101:AA101)
A102: C14 | B102: Робот-уборщик (аренда) | C102: TXNREV | D102: =D99*'Допущения'!$G$28 | E102: =E99*'Допущения'!$G$28 | F102: =F99*'Допущения'!$G$28 | G102: =G99*'Допущения'!$G$28 | H102: =H99*'Допущения'!$G$28 | I102: =I99*'Допущения'!$G$28 | J102: =J99*'Допущения'!$G$28 | K102: =K99*'Допущения'!$G$28 | ... AA102: =AA99*'Допущения'!$G$28 | AB102: =SUM(D102:AA102)
...

Sheet PnL
B1: Модель запуска в Лигурии: hardware + agent-сервисы для отелей (EUR, без НДС)
B3: Месяц | D3: 1 | E3: 2 | F3: 3 | G3: 4 | H3: 5 | I3: 6 | J3: 7 | K3: 8 | L3: 9 | M3: 10 | N3: 11 | O3: 12 | P3: 13 | Q3: 14 | R3: 15 | S3: 16 | T3: 17 | U3: 18 | V3: 19 | W3: 20 | X3: 21 | Y3: 22 | Z3: 23 | AA3: 24 | AB3: Год 1 | AC3: Год 2 | AD3: 24 мес.
B5: Выручка: hardware и setup | D5: =SUMIF('Модель'!$C$7:$C$111,"HWREV",'Модель'!D$7:D$111) | E5: =SUMIF('Модель'!$C$7:$C$111,"HWREV",'Модель'!E$7:E$111) | F5: =SUMIF('Модель'!$C$7:$C$111,"HWREV",'Модель'!F$7:F$111) | G5: =SUMIF('Модель'!$C$7:$C$111,"HWREV",'Модель'!G$7:G$111) | H5: =SUMIF('Модель'!$C$7:$C$111,"HWREV",'Модель'!H$7:H$111) | I5: =SUMIF('Модель'!$C$7:$C$111,"HWREV",'Модель'!I$7:I$111) | J5: =SUMIF('Модель'!$C$7:$C$111,"HWREV",'Модель'!J$7:J$111) | K5: =SUMIF('Модель'!$C$7:$C$111,"HWREV",'Модель'!K$7:K$111) | ... AA5: =SUMIF('Модель'!$C$7:$C$111,"HWREV",'Модель'!AA$7:AA$111) | AB5: =SUM(D5:O5) | AC5: =SUM(P5:AA5) | AD5: =SUM(D5:AA5)
B6: Выручка: recurring (SaaS/lease) | D6: =SUMIF('Модель'!$C$7:$C$111,"RECREV",'Модель'!D$7:D$111) | E6: =SUMIF('Модель'!$C$7:$C$111,"RECREV",'Модель'!E$7:E$111) | F6: =SUMIF('Модель'!$C$7:$C$111,"RECREV",'Модель'!F$7:F$111) | G6: =SUMIF('Модель'!$C$7:$C$111,"RECREV",'Модель'!G$7:G$111) | H6: =SUMIF('Модель'!$C$7:$C$111,"RECREV",'Модель'!H$7:H$111) | I6: =SUMIF('Модель'!$C$7:$C$111,"RECREV",'Модель'!I$7:I$111) | J6: =SUMIF('Модель'!$C$7:$C$111,"RECREV",'Модель'!J$7:J$111) | K6: =SUMIF('Модель'!$C$7:$C$111,"RECREV",'Модель'!K$7:K$111) | ... AA6: =SUMIF('Модель'!$C$7:$C$111,"RECREV",'Модель'!AA$7:AA$111) | AB6: =SUM(D6:O6) | AC6: =SUM(P6:AA6) | AD6: =SUM(D6:AA6)
B7: Маржа транзакций | D7: =SUMIF('Модель'!$C$7:$C$111,"TXNREV",'Модель'!D$7:D$111) | E7: =SUMIF('Модель'!$C$7:$C$111,"TXNREV",'Модель'!E$7:E$111) | F7: =SUMIF('Модель'!$C$7:$C$111,"TXNREV",'Модель'!F$7:F$111) | G7: =SUMIF('Модель'!$C$7:$C$111,"TXNREV",'Модель'!G$7:G$111) | H7: =SUMIF('Модель'!$C$7:$C$111,"TXNREV",'Модель'!H$7:H$111) | I7: =SUMIF('Модель'!$C$7:$C$111,"TXNREV",'Модель'!I$7:I$111) | J7: =SUMIF('Модель'!$C$7:$C$111,"TXNREV",'Модель'!J$7:J$111) | K7: =SUMIF('Модель'!$C$7:$C$111,"TXNREV",'Модель'!K$7:K$111) | ... AA7: =SUMIF('Модель'!$C$7:$C$111,"TXNREV",'Модель'!AA$7:AA$111) | AB7: =SUM(D7:O7) | AC7: =SUM(P7:AA7) | AD7: =SUM(D7:AA7)
B8: Выручка всего | D8: =SUM(D5:D7) | E8: =SUM(E5:E7) | F8: =SUM(F5:F7) | G8: =SUM(G5:G7) | H8: =SUM(H5:H7) | I8: =SUM(I5:I7) | J8: =SUM(J5:J7) | K8: =SUM(K5:K7) | ... AA8: =SUM(AA5:AA7) | AB8: =SUM(D8:O8) | AC8: =SUM(P8:AA8) | AD8: =SUM(D8:AA8)
B9: Landed HW + установка | D9: =SUMIF('Модель'!$C$7:$C$111,"COGS",'Модель'!D$7:D$111) | E9: =SUMIF('Модель'!$C$7:$C$111,"COGS",'Модель'!E$7:E$111) | F9: =SUMIF('Модель'!$C$7:$C$111,"COGS",'Модель'!F$7:F$111) | G9: =SUMIF('Модель'!$C$7:$C$111,"COGS",'Модель'!G$7:G$111) | H9: =SUMIF('Модель'!$C$7:$C$111,"COGS",'Модель'!H$7:H$111) | I9: =SUMIF('Модель'!$C$7:$C$111,"COGS",'Модель'!I$7:I$111) | J9: =SUMIF('Модель'!$C$7:$C$111,"COGS",'Модель'!J$7:J$111) | K9: =SUMIF('Модель'!$C$7:$C$111,"COGS",'Модель'!K$7:K$111) | ... AA9: =SUMIF('Модель'!$C$7:$C$111,"COGS",'Модель'!AA$7:AA$111) | AB9: =SUM(D9:O9) | AC9: =SUM(P9:AA9) | AD9: =SUM(D9:AA9)
B10: Переменные затраты | D10: =SUMIF('Модель'!$C$7:$C$111,"VARC",'Модель'!D$7:D$111) | E10: =SUMIF('Модель'!$C$7:$C$111,"VARC",'Модель'!E$7:E$111) | F10: =SUMIF('Модель'!$C$7:$C$111,"VARC",'Модель'!F$7:F$111) | G10: =SUMIF('Модель'!$C$7:$C$111,"VARC",'Модель'!G$7:G$111) | H10: =SUMIF('Модель'!$C$7:$C$111,"VARC",'Модель'!H$7:H$111) | I10: =SUMIF('Модель'!$C$7:$C$111,"VARC",'Модель'!I$7:I$111) | J10: =SUMIF('Модель'!$C$7:$C$111,"VARC",'Модель'!J$7:J$111) | K10: =SUMIF('Модель'!$C$7:$C$111,"VARC",'Модель'!K$7:K$111) | ... AA10: =SUMIF('Модель'!$C$7:$C$111,"VARC",'Модель'!AA$7:AA$111) | AB10: =SUM(D10:O10) | AC10: =SUM(P10:AA10) | AD10: =SUM(D10:AA10)
B11: Валовая прибыль | D11: =D8-D9-D10 | E11: =E8-E9-E10 | F11: =F8-F9-F10 | G11: =G8-G9-G10 | H11: =H8-H9-H10 | I11: =I8-I9-I10 | J11: =J8-J9-J10 | K11: =K8-K9-K10 | ... AA11: =AA8-AA9-AA10 | AB11: =SUM(D11:O11) | AC11: =SUM(P11:AA11) | AD11: =SUM(D11:AA11)
B12: Валовая маржа % | D12: =IF(D8=0,0,D11/D8) | E12: =IF(E8=0,0,E11/E8) | F12: =IF(F8=0,0,F11/F8) | G12: =IF(G8=0,0,G11/G8) | H12: =IF(H8=0,0,H11/H8) | I12: =IF(I8=0,0,I11/I8) | J12: =IF(J8=0,0,J11/J8) | K12: =IF(K8=0,0,K11/K8) | ... AD12: =IF(AD8=0,0,AD11/AD8)
B13: Постоянные opex | D13: =SUMPRODUCT(('Допущения'!$D$34:$D$42<=D$3)*'Допущения'!$C$34:$C$42) | E13: =SUMPRODUCT(('Допущения'!$D$34:$D$42<=E$3)*'Допущения'!$C$34:$C$42) | F13: =SUMPRODUCT(('Допущения'!$D$34:$D$42<=F$3)*'Допущения'!$C$34:$C$42) | G13: =SUMPRODUCT(('Допущения'!$D$34:$D$42<=G$3)*'Допущения'!$C$34:$C$42) | H13: =SUMPRODUCT(('Допущения'!$D$34:$D$42<=H$3)*'Допущения'!$C$34:$C$42) | I13: =SUMPRODUCT(('Допущения'!$D$34:$D$42<=I$3)*'Допущения'!$C$34:$C$42) | J13: =SUMPRODUCT(('Допущения'!$D$34:$D$42<=J$3)*'Допущения'!$C$34:$C$42) | K13: =SUMPRODUCT(('Допущения'!$D$34:$D$42<=K$3)*'Допущения'!$C$34:$C$42) | ... AA13: =SUMPRODUCT(('Допущения'!$D$34:$D$42<=AA$3)*'Допущения'!$C$34:$C$42) | AB13: =SUM(D13:O13) | AC13: =SUM(P13:AA13) | AD13: =SUM(D13:AA13)
B14: Разовые расходы запуска | D14: =IF(D$3=1,SUM('Допущения'!$C$46:$C$50),0) | E14: =IF(E$3=1,SUM('Допущения'!$C$46:$C$50),0) | F14: =IF(F$3=1,SUM('Допущения'!$C$46:$C$50),0) | G14: =IF(G$3=1,SUM('Допущения'!$C$46:$C$50),0) | H14: =IF(H$3=1,SUM('Допущения'!$C$46:$C$50),0) | I14: =IF(I$3=1,SUM('Допущения'!$C$46:$C$50),0) | J14: =IF(J$3=1,SUM('Допущения'!$C$46:$C$50),0) | K14: =IF(K$3=1,SUM('Допущения'!$C$46:$C$50),0) | ... AA14: =IF(AA$3=1,SUM('Допущения'!$C$46:$C$50),0) | AB14: =SUM(D14:O14) | AC14: =SUM(P14:AA14) | AD14: =SUM(D14:AA14)
B15: EBITDA | D15: =D11-D13-D14 | E15: =E11-E13-E14 | F15: =F11-F13-F14 | G15: =G11-G13-G14 | H15: =H11-H13-H14 | I15: =I11-I13-I14 | J15: =J11-J13-J14 | K15: =K11-K13-K14 | ... AA15: =AA11-AA13-AA14 | AB15: =SUM(D15:O15) | AC15: =SUM(P15:AA15) | AD15: =SUM(D15:AA15)
B16: Налог (упрощённо) | D16: =MAX(0,D15)*'Допущения'!$C$8 | E16: =MAX(0,E15)*'Допущения'!$C$8 | F16: =MAX(0,F15)*'Допущения'!$C$8 | G16: =MAX(0,G15)*'Допущения'!$C$8 | H16: =MAX(0,H15)*'Допущения'!$C$8 | I16: =MAX(0,I15)*'Допущения'!$C$8 | J16: =MAX(0,J15)*'Допущения'!$C$8 | K16: =MAX(0,K15)*'Допущения'!$C$8 | ... AA16: =MAX(0,AA15)*'Допущения'!$C$8 | AB16: =SUM(D16:O16) | AC16: =SUM(P16:AA16) | AD16: =SUM(D16:AA16)
B17: Чистый результат | D17: =D15-D16 | E17: =E15-E16 | F17: =F15-F16 | G17: =G15-G16 | H17: =H15-H16 | I17: =I15-I16 | J17: =J15-J16 | K17: =K15-K16 | ... AA17: =AA15-AA16 | AB17: =SUM(D17:O17) | AC17: =SUM(P17:AA17) | AD17: =SUM(D17:AA17)
B18: Накопленный результат | D18: =D17 | E18: =D18+E17 | F18: =E18+F17 | G18: =F18+G17 | H18: =G18+H17 | I18: =H18+I17 | J18: =I18+J17 | K18: =J18+K17 | L18: =K18+L17 | ... AA18: =Z18+AA17
B19: Вспом.: месяц, если EBITDA>0 | D19: =IF(D15>0,D$3,99) | E19: =IF(E15>0,E$3,99) | F19: =IF(F15>0,F$3,99) | G19: =IF(G15>0,G$3,99) | H19: =IF(H15>0,H$3,99) | I19: =IF(I15>0,I$3,99) | J19: =IF(J15>0,J$3,99) | K19: =IF(K15>0,K$3,99) | ... AA19: =IF(AA15>0,AA$3,99)

Sheet Cashflow
B1: Модель запуска в Лигурии: hardware + agent-сервисы для отелей (EUR, без НДС)
B3: Месяц | D3: 1 | E3: 2 | F3: 3 | G3: 4 | H3: 5 | I3: 6 | J3: 7 | K3: 8 | L3: 9 | M3: 10 | N3: 11 | O3: 12 | P3: 13 | Q3: 14 | R3: 15 | S3: 16 | T3: 17 | U3: 18 | V3: 19 | W3: 20 | X3: 21 | Y3: 22 | Z3: 23 | AA3: 24
B5: Поступления | D5: ='Допущения'!$C$9*'PnL'!D8 | E5: ='Допущения'!$C$9*'PnL'!E8+(1-'Допущения'!$C$9)*'PnL'!D8 | F5: ='Допущения'!$C$9*'PnL'!F8+(1-'Допущения'!$C$9)*'PnL'!E8 | G5: ='Допущения'!$C$9*'PnL'!G8+(1-'Допущения'!$C$9)*'PnL'!F8 | H5: ='Допущения'!$C$9*'PnL'!H8+(1-'Допущения'!$C$9)*'PnL'!G8 | I5: ='Допущения'!$C$9*'PnL'!I8+(1-'Допущения'!$C$9)*'PnL'!H8 | J5: ='Допущения'!$C$9*'PnL'!J8+(1-'Допущения'!$C$9)*'PnL'!I8 | K5: ='Допущения'!$C$9*'PnL'!K8+(1-'Допущения'!$C$9)*'PnL'!J8 | L5: ='Допущения'!$C$9*'PnL'!L8+(1-'Допущения'!$C$9)*'PnL'!K8 | ... AA5: ='Допущения'!$C$9*'PnL'!AA8+(1-'Допущения'!$C$9)*'PnL'!Z8
B6: Закупки hardware (оплата за 2 мес. вперёд) | D6: ='PnL'!D9+'PnL'!E9+'PnL'!F9 | E6: ='PnL'!G9 | F6: ='PnL'!H9 | G6: ='PnL'!I9 | H6: ='PnL'!J9 | I6: ='PnL'!K9 | J6: ='PnL'!L9 | K6: ='PnL'!M9 | L6: ='PnL'!N9 | ... Y6: ='PnL'!AA9 | Z6: 0 | AA6: 0
B7: Переменные затраты | D7: ='PnL'!D10 | E7: ='PnL'!E10 | F7: ='PnL'!F10 | G7: ='PnL'!G10 | H7: ='PnL'!H10 | I7: ='PnL'!I10 | J7: ='PnL'!J10 | K7: ='PnL'!K10 | ... AA7: ='PnL'!AA10
B8: Постоянные opex | D8: ='PnL'!D13 | E8: ='PnL'!E13 | F8: ='PnL'!F13 | G8: ='PnL'!G13 | H8: ='PnL'!H13 | I8: ='PnL'!I13 | J8: ='PnL'!J13 | K8: ='PnL'!K13 | ... AA8: ='PnL'!AA13
B9: Разовые расходы | D9: ='PnL'!D14 | E9: ='PnL'!E14 | F9: ='PnL'!F14 | G9: ='PnL'!G14 | H9: ='PnL'!H14 | I9: ='PnL'!I14 | J9: ='PnL'!J14 | K9: ='PnL'!K14 | ... AA9: ='PnL'!AA14
B10: Налоги | D10: ='PnL'!D16 | E10: ='PnL'!E16 | F10: ='PnL'!F16 | G10: ='PnL'!G16 | H10: ='PnL'!H16 | I10: ='PnL'!I16 | J10: ='PnL'!J16 | K10: ='PnL'!K16 | ... AA10: ='PnL'!AA16
B11: Чистый денежный поток | D11: =D5-D6-D7-D8-D9-D10 | E11: =E5-E6-E7-E8-E9-E10 | F11: =F5-F6-F7-F8-F9-F10 | G11: =G5-G6-G7-G8-G9-G10 | H11: =H5-H6-H7-H8-H9-H10 | I11: =I5-I6-I7-I8-I9-I10 | J11: =J5-J6-J7-J8-J9-J10 | K11: =K5-K6-K7-K8-K9-K10 | ... AA11: =AA5-AA6-AA7-AA8-AA9-AA10
B12: Остаток на начало | D12: ='Допущения'!$C$7 | E12: =D13 | F12: =E13 | G12: =F13 | H12: =G13 | I12: =H13 | J12: =I13 | K12: =J13 | L12: =K13 | ... AA12: =Z13
B13: Остаток на конец | D13: =D12+D11 | E13: =E12+E11 | F13: =F12+F11 | G13: =G12+G11 | H13: =H12+H11 | I13: =I12+I11 | J13: =J12+J11 | K13: =K12+K11 | ... AA13: =AA12+AA11
B14: Накопленный денежный поток | D14: =D11 | E14: =D14+E11 | F14: =E14+F11 | G14: =F14+G11 | H14: =G14+H11 | I14: =H14+I11 | J14: =I14+J11 | K14: =J14+K11 | L14: =K14+L11 | ... AA14: =Z14+AA11

Sheet Экон_категорий
B1: Модель запуска в Лигурии: hardware + agent-сервисы для отелей (EUR, без НДС)
B3: Категория | C3: Первоначальные затраты / ед. | D3: Разовая цена / ед. | E3: Маржа на разовой части / ед. | F3: Ежемесячный вклад / ед. | G3: Payback (мес.) | H3: Landed-затраты за 24 мес. (инвестиции) | I3: Выручка за 24 мес. | J3: Вклад за 24 мес. | K3: Вклад / инвестиции | L3: Активные ед., месяц 24 | M3: ID
B4: Hotel Agent OS (платформа агентов) | C4: ='Допущения'!C15+'Допущения'!D15 | D4: ='Допущения'!E15 | E4: =D4-C4 | F4: ='Допущения'!F15+'Допущения'!G15-'Допущения'!H15 | G4: =IF(F4<=0,"н/д",MAX(0,C4-D4)/F4) | H4: =SUMIFS('Модель'!$AB$7:$AB$111,'Модель'!$A$7:$A$111,$M4,'Модель'!$C$7:$C$111,"COGS") | I4: =SUMIFS('Модель'!$AB$7:$AB$111,'Модель'!$A$7:$A$111,$M4,'Модель'!$C$7:$C$111,"HWREV")+SUMIFS('Модель'!$AB$7:$AB$111,'Модель'!$A$7:$A$111,$M4,'Модель'!$C$7:$C$111,"RECREV")+SUMIFS('Модель'!$AB$7:$AB$111,'Модель'!$A$7:$A$111,$M4,'Модель'!$C$7:$C$111,"TXNREV") | J4: =I4-H4-SUMIFS('Модель'!$AB$7:$AB$111,'Модель'!$A$7:$A$111,$M4,'Модель'!$C$7:$C$111,"VARC") | K4: =IF(H4=0,"н/д",J4/H4) | L4: =SUMIFS('Модель'!$AA$7:$AA$111,'Модель'!$A$7:$A$111,$M4,'Модель'!$C$7:$C$111,"ACTU") | M4: C01
B5: GuestNode Lobby (ресепшен) | C5: ='Допущения'!C16+'Допущения'!D16 | D5: ='Допущения'!E16 | E5: =D5-C5 | F5: ='Допущения'!F16+'Допущения'!G16-'Допущения'!H16 | G5: =IF(F5<=0,"н/д",MAX(0,C5-D5)/F5) | H5: =SUMIFS('Модель'!$AB$7:$AB$111,'Модель'!$A$7:$A$111,$M5,'Модель'!$C$7:$C$111,"COGS") | I5: =SUMIFS('Модель'!$AB$7:$AB$111,'Модель'!$A$7:$A$111,$M5,'Модель'!$C$7:$C$111,"HWREV")+SUMIFS('Модель'!$AB$7:$AB$111,'Модель'!$A$7:$A$111,$M5,'Модель'!$C$7:$C$111,"RECREV")+SUMIFS('Модель'!$AB$7:$AB$111,'Модель'!$A$7:$A$111,$M5,'Модель'!$C$7:$C$111,"TXNREV") | J5: =I5-H5-SUMIFS('Модель'!$AB$7:$AB$111,'Модель'!$A$7:$A$111,$M5,'Модель'!$C$7:$C$111,"VARC") | K5: =IF(H5=0,"н/д",J5/H5) | L5: =SUMIFS('Модель'!$AA$7:$AA$111,'Модель'!$A$7:$A$111,$M5,'Модель'!$C$7:$C$111,"ACTU") | M5: C02
B6: GuestNode в номере | C6: ='Допущения'!C17+'Допущения'!D17 | D6: ='Допущения'!E17 | E6: =D6-C6 | F6: ='Допущения'!F17+'Допущения'!G17-'Допущения'!H17 | G6: =IF(F6<=0,"н/д",MAX(0,C6-D6)/F6) | H6: =SUMIFS('Модель'!$AB$7:$AB$111,'Модель'!$A$7:$A$111,$M6,'Модель'!$C$7:$C$111,"COGS") | I6: =SUMIFS('Модель'!$AB$7:$AB$111,'Модель'!$A$7:$A$111,$M6,'Модель'!$C$7:$C$111,"HWREV")+SUMIFS('Модель'!$AB$7:$AB$111,'Модель'!$A$7:$A$111,$M6,'Модель'!$C$7:$C$111,"RECREV")+SUMIFS('Модель'!$AB$7:$AB$111,'Модель'!$A$7:$A$111,$M6,'Модель'!$C$7:$C$111,"TXNREV") | J6: =I6-H6-SUMIFS('Модель'!$AB$7:$AB$111,'Модель'!$A$7:$A$111,$M6,'Модель'!$C$7:$C$111,"VARC") | K6: =IF(H6=0,"н/д",J6/H6) | L6: =SUMIFS('Модель'!$AA$7:$AA$111,'Модель'!$A$7:$A$111,$M6,'Модель'!$C$7:$C$111,"ACTU") | M6: C03
B7: Smart Travel Wall (микро-магазин) | C7: ='Допущения'!C18+'Допущения'!D18 | D7: ='Допущения'!E18 | E7: =D7-C7 | F7: ='Допущения'!F18+'Допущения'!G18-'Допущения'!H18 | G7: =IF(F7<=0,"н/д",MAX(0,C7-D7)/F7) | H7: =SUMIFS('Модель'!$AB$7:$AB$111,'Модель'!$A$7:$A$111,$M7,'Модель'!$C$7:$C$111,"COGS") | I7: =SUMIFS('Модель'!$AB$7:$AB$111,'Модель'!$A$7:$A$111,$M7,'Модель'!$C$7:$C$111,"HWREV")+SUMIFS('Модель'!$AB$7:$AB$111,'Модель'!$A$7:$A$111,$M7,'Модель'!$C$7:$C$111,"RECREV")+SUMIFS('Модель'!$AB$7:$AB$111,'Модель'!$A$7:$A$111,$M7,'Модель'!$C$7:$C$111,"TXNREV") | J7: =I7-H7-SUMIFS('Модель'!$AB$7:$AB$111,'Модель'!$A$7:$A$111,$M7,'Модель'!$C$7:$C$111,"VARC") | K7: =IF(H7=0,"н/д",J7/H7) | L7: =SUMIFS('Модель'!$AA$7:$AA$111,'Модель'!$A$7:$A$111,$M7,'Модель'!$C$7:$C$111,"ACTU") | M7: C04
B8: Rental-локеры | C8: ='Допущения'!C19+'Допущения'!D19 | D8: ='Допущения'!E19 | E8: =D8-C8 | F8: ='Допущения'!F19+'Допущения'!G19-'Допущения'!H19 | G8: =IF(F8<=0,"н/д",MAX(0,C8-D8)/F8) | H8: =SUMIFS('Модель'!$AB$7:$AB$111,'Модель'!$A$7:$A$111,$M8,'Модель'!$C$7:$C$111,"COGS") | I8: =SUMIFS('Модель'!$AB$7:$AB$111,'Модель'!$A$7:$A$111,$M8,'Модель'!$C$7:$C$111,"HWREV")+SUMIFS('Модель'!$AB$7:$AB$111,'Модель'!$A$7:$A$111,$M8,'Модель'!$C$7:$C$111,"RECREV")+SUMIFS('Модель'!$AB$7:$AB$111,'Модель'!$A$7:$A$111,$M8,'Модель'!$C$7:$C$111,"TXNREV") | J8: =I8-H8-SUMIFS('Модель'!$AB$7:$AB$111,'Модель'!$A$7:$A$111,$M8,'Модель'!$C$7:$C$111,"VARC") | K8: =IF(H8=0,"н/д",J8/H8) | L8: =SUMIFS('Модель'!$AA$7:$AA$111,'Модель'!$A$7:$A$111,$M8,'Модель'!$C$7:$C$111,"ACTU") | M8: C05
B9: Локеры для багажа | C9: ='Допущения'!C20+'Допущения'!D20 | D9: ='Допущения'!E20 | E9: =D9-C9 | F9: ='Допущения'!F20+'Допущения'!G20-'Допущения'!H20 | G9: =IF(F9<=0,"н/д",MAX(0,C9-D9)/F9) | H9: =SUMIFS('Модель'!$AB$7:$AB$111,'Модель'!$A$7:$A$111,$M9,'Модель'!$C$7:$C$111,"COGS") | I9: =SUMIFS('Модель'!$AB$7:$AB$111,'Модель'!$A$7:$A$111,$M9,'Модель'!$C$7:$C$111,"HWREV")+SUMIFS('Модель'!$AB$7:$AB$111,'Модель'!$A$7:$A$111,$M9,'Модель'!$C$7:$C$111,"RECREV")+SUMIFS('Модель'!$AB$7:$AB$111,'Модель'!$A$7:$A$111,$M9,'Модель'!$C$7:$C$111,"TXNREV") | J9: =I9-H9-SUMIFS('Модель'!$AB$7:$AB$111,'Модель'!$A$7:$A$111,$M9,'Модель'!$C$7:$C$111,"VARC") | K9: =IF(H9=0,"н/д",J9/H9) | L9: =SUMIFS('Модель'!$AA$7:$AA$111,'Модель'!$A$7:$A$111,$M9,'Модель'!$C$7:$C$111,"ACTU") | M9: C06
B10: Аренда power bank | C10: ='Допущения'!C21+'Допущения'!D21 | D10: ='Допущения'!E21 | E10: =D10-C10 | F10: ='Допущения'!F21+'Допущения'!G21-'Допущения'!H21 | G10: =IF(F10<=0,"н/д",MAX(0,C10-D10)/F10) | H10: =SUMIFS('Модель'!$AB$7:$AB$111,'Модель'!$A$7:$A$111,$M10,'Модель'!$C$7:$C$111,"COGS") | I10: =SUMIFS('Модель'!$AB$7:$AB$111,'Модель'!$A$7:$A$111,$M10,'Модель'!$C$7:$C$111,"HWREV")+SUMIFS('Модель'!$AB$7:$AB$111,'Модель'!$A$7:$A$111,$M10,'Модель'!$C$7:$C$111,"RECREV")+SUMIFS('Модель'!$AB$7:$AB$111,'Модель'!$A$7:$A$111,$M10,'Модель'!$C$7:$C$111,"TXNREV") | J10: =I10-H10-SUMIFS('Модель'!$AB$7:$AB$111,'Модель'!$A$7:$A$111,$M10,'Модель'!$C$7:$C$111,"VARC") | K10: =IF(H10=0,"н/д",J10/H10) | L10: =SUMIFS('Модель'!$AA$7:$AA$111,'Модель'!$A$7:$A$111,$M10,'Модель'!$C$7:$C$111,"ACTU") | M10: C07
B11: IoT-комплект энергосбережения (на номер) | C11: ='Допущения'!C22+'Допущения'!D22 | D11: ='Допущения'!E22 | E11: =D11-C11 | F11: ='Допущения'!F22+'Допущения'!G22-'Допущения'!H22 | G11: =IF(F11<=0,"н/д",MAX(0,C11-D11)/F11) | H11: =SUMIFS('Модель'!$AB$7:$AB$111,'Модель'!$A$7:$A$111,$M11,'Модель'!$C$7:$C$111,"COGS") | I11: =SUMIFS('Модель'!$AB$7:$AB$111,'Модель'!$A$7:$A$111,$M11,'Модель'!$C$7:$C$111,"HWREV")+SUMIFS('Модель'!$AB$7:$AB$111,'Модель'!$A$7:$A$111,$M11,'Модель'!$C$7:$C$111,"RECREV")+SUMIFS('Модель'!$AB$7:$AB$111,'Модель'!$A$7:$A$111,$M11,'Модель'!$C$7:$C$111,"TXNREV") | J11: =I11-H11-SUMIFS('Модель'!$AB$7:$AB$111,'Модель'!$A$7:$A$111,$M11,'Модель'!$C$7:$C$111,"VARC") | K11: =IF(H11=0,"н/д",J11/H11) | L11: =SUMIFS('Модель'!$AA$7:$AA$111,'Модель'!$A$7:$A$111,$M11,'Модель'!$C$7:$C$111,"ACTU") | M11: C08
B12: Smart access (на дверь) | C12: ='Допущения'!C23+'Допущения'!D23 | D12: ='Допущения'!E23 | E12: =D12-C12 | F12: ='Допущения'!F23+'Допущения'!G23-'Допущения'!H23 | G12: =IF(F12<=0,"н/д",MAX(0,C12-D12)/F12) | H12: =SUMIFS('Модель'!$AB$7:$AB$111,'Модель'!$A$7:$A$111,$M12,'Модель'!$C$7:$C$111,"COGS") | I12: =SUMIFS('Модель'!$AB$7:$AB$111,'Модель'!$A$7:$A$111,$M12,'Модель'!$C$7:$C$111,"HWREV")+SUMIFS('Модель'!$AB$7:$AB$111,'Модель'!$A$7:$A$111,$M12,'Модель'!$C$7:$C$111,"RECREV")+SUMIFS('Модель'!$AB$7:$AB$111,'Модель'!$A$7:$A$111,$M12,'Модель'!$C$7:$C$111,"TXNREV") | J12: =I12-H12-SUMIFS('Модель'!$AB$7:$AB$111,'Модель'!$A$7:$A$111,$M12,'Модель'!$C$7:$C$111,"VARC") | K12: =IF(H12=0,"н/д",J12/H12) | L12: =SUMIFS('Модель'!$AA$7:$AA$111,'Модель'!$A$7:$A$111,$M12,'Модель'!$C$7:$C$111,"ACTU") | M12: C09
B13: Датчики Healthy Room (на номер) | C13: ='Допущения'!C24+'Допущения'!D24 | D13: ='Допущения'!E24 | E13: =D13-C13 | F13: ='Допущения'!F24+'Допущения'!G24-'Допущения'!H24 | G13: =IF(F13<=0,"н/д",MAX(0,C13-D13)/F13) | H13: =SUMIFS('Модель'!$AB$7:$AB$111,'Модель'!$A$7:$A$111,$M13,'Модель'!$C$7:$C$111,"COGS") | I13: =SUMIFS('Модель'!$AB$7:$AB$111,'Модель'!$A$7:$A$111,$M13,'Модель'!$C$7:$C$111,"HWREV")+SUMIFS('Модель'!$AB$7:$AB$111,'Модель'!$A$7:$A$111,$M13,'Модель'!$C$7:$C$111,"RECREV")+SUMIFS('Модель'!$AB$7:$AB$111,'Модель'!$A$7:$A$111,$M13,'Модель'!$C$7:$C$111,"TXNREV") | J13: =I13-H13-SUMIFS('Модель'!$AB$7:$AB$111,'Модель'!$A$7:$A$111,$M13,'Модель'!$C$7:$C$111,"VARC") | K13: =IF(H13=0,"н/д",J13/H13) | L13: =SUMIFS('Модель'!$AA$7:$AA$111,'Модель'!$A$7:$A$111,$M13,'Модель'!$C$7:$C$111,"ACTU") | M13: C10
B14: Киоск check-in / ID | C14: ='Допущения'!C25+'Допущения'!D25 | D14: ='Допущения'!E25 | E14: =D14-C14 | F14: ='Допущения'!F25+'Допущения'!G25-'Допущения'!H25 | G14: =IF(F14<=0,"н/д",MAX(0,C14-D14)/F14) | H14: =SUMIFS('Модель'!$AB$7:$AB$111,'Модель'!$A$7:$A$111,$M14,'Модель'!$C$7:$C$111,"COGS") | I14: =SUMIFS('Модель'!$AB$7:$AB$111,'Модель'!$A$7:$A$111,$M14,'Модель'!$C$7:$C$111,"HWREV")+SUMIFS('Модель'!$AB$7:$AB$111,'Модель'!$A$7:$A$111,$M14,'Модель'!$C$7:$C$111,"RECREV")+SUMIFS('Модель'!$AB$7:$AB$111,'Модель'!$A$7:$A$111,$M14,'Модель'!$C$7:$C$111,"TXNREV") | J14: =I14-H14-SUMIFS('Модель'!$AB$7:$AB$111,'Модель'!$A$7:$A$111,$M14,'Модель'!$C$7:$C$111,"VARC") | K14: =IF(H14=0,"н/д",J14/H14) | L14: =SUMIFS('Модель'!$AA$7:$AA$111,'Модель'!$A$7:$A$111,$M14,'Модель'!$C$7:$C$111,"ACTU") | M14: C11
B15: Локальный marketplace | C15: ='Допущения'!C26+'Допущения'!D26 | D15: ='Допущения'!E26 | E15: =D15-C15 | F15: ='Допущения'!F26+'Допущения'!G26-'Допущения'!H26 | G15: =IF(F15<=0,"н/д",MAX(0,C15-D15)/F15) | H15: =SUMIFS('Модель'!$AB$7:$AB$111,'Модель'!$A$7:$A$111,$M15,'Модель'!$C$7:$C$111,"COGS") | I15: =SUMIFS('Модель'!$AB$7:$AB$111,'Модель'!$A$7:$A$111,$M15,'Модель'!$C$7:$C$111,"HWREV")+SUMIFS('Модель'!$AB$7:$AB$111,'Модель'!$A$7:$A$111,$M15,'Модель'!$C$7:$C$111,"RECREV")+SUMIFS('Модель'!$AB$7:$AB$111,'Модель'!$A$7:$A$111,$M15,'Модель'!$C$7:$C$111,"TXNREV") | J15: =I15-H15-SUMIFS('Модель'!$AB$7:$AB$111,'Модель'!$A$7:$A$111,$M15,'Модель'!$C$7:$C$111,"VARC") | K15: =IF(H15=0,"н/д",J15/H15) | L15: =SUMIFS('Модель'!$AA$7:$AA$111,'Модель'!$A$7:$A$111,$M15,'Модель'!$C$7:$C$111,"ACTU") | M15: C12
... B18: Регулируемый vending (только fee лицензированного партнёра) | C18: ='Допущения'!C29+'Допущения'!D29 | D18: ='Допущения'!E29 | E18: =D18-C18 | F18: ='Допущения'!F29+'Допущения'!G29-'Допущения'!H29 | G18: =IF(F18<=0,"н/д",MAX(0,C18-D18)/F18) | H18: =SUMIFS('Модель'!$AB$7:$AB$111,'Модель'!$A$7:$A$111,$M18,'Модель'!$C$7:$C$111,"COGS") | I18: =SUMIFS('Модель'!$AB$7:$AB$111,'Модель'!$A$7:$A$111,$M18,'Модель'!$C$7:$C$111,"HWREV")+SUMIFS('Модель'!$AB$7:$AB$111,'Модель'!$A$7:$A$111,$M18,'Модель'!$C$7:$C$111,"RECREV")+SUMIFS('Модель'!$AB$7:$AB$111,'Модель'!$A$7:$A$111,$M18,'Модель'!$C$7:$C$111,"TXNREV") | J18: =I18-H18-SUMIFS('Модель'!$AB$7:$AB$111,'Модель'!$A$7:$A$111,$M18,'Модель'!$C$7:$C$111,"VARC") | K18: =IF(H18=0,"н/д",J18/H18) | L18: =SUMIFS('Модель'!$AA$7:$AA$111,'Модель'!$A$7:$A$111,$M18,'Модель'!$C$7:$C$111,"ACTU") | M18: C15

Sheet Лицензии
A1: Категория | B1: Требование (ориентир.) | C1: Решение для go-to-market
A2: Agent-SaaS / данные гостей | B2: GDPR, DPA с отелями, прозрачность ИИ, меры безопасности | C2: Хостинг в ЕС, минимизация данных, audit-логи
A3: Идентификация гостей | B3: TULPS ст. 109 / Alloggiati Web, GDPR; без долгого хранения копий документов | C3: Проверка только при check-in; устройство в номере получает краткоживущий токен
A4: Радио-оборудование (Wi-Fi/BLE/Zigbee) | B4: CE, RED, EMC, LVD, RoHS, DoC и технический файл | C4: Ввозить только SKU с отчётами для конкретной модели
A5: White-label / private label | B5: Импортёр может принять на себя обязанности производителя | C5: Завершить аудит соответствия до ребрендинга
A6: Подключённые устройства (CRA) | B6: Cyber Resilience Act: отчётность с 11.09.2026, основные требования с 11.12.2027 | C6: SBOM, OTA-обновления, контакт по уязвимостям
A7: Платежи | B7: Договор с PSP/эквайером, сертифицированный терминал | C7: Использовать сертифицированный сторонний терминал
A8: Vending еды/напитков | B8: SCIA/SUAP, HACCP, маркировка (местные правила) | C8: Партнёрство с местным лицензированным оператором
A9: Vending алкоголя | B9: Возрастные ограничения и местные разрешения | C9: Только после юр. заключения
A10: Табак / электронные сигареты | B10: Режим ADM, авторизованные поставки, проверка возраста, ограничения рекламы и дистанционных продаж, акциз на жидкости | C10: Только партнёрство с лицензированным оператором; без прямых продаж
A11: Умные замки | B11: RED/EMC, совместимость с противопожарными дверями и аварийным выходом | C11: Сертифицированные замки, местный слесарь
A12: Роботы | B12: CE, безопасность машин/продукции, ответственность и оценка рисков | C12: Сначала пилот под наблюдением

Sheet Риски
A1: Риск | B1: Вероятность | C1: Влияние | D1: Mitigation
A2: Долгий цикл продаж | B2: Высокая | C2: Высокая | D2: Платные пилоты, сезонные дедлайны, партнёры PMS
A3: Низкое использование GuestNode | B3: Средняя | C3: Высокая | D3: Сначала lobby, QR-fallback, пороги использования
A4: Отказы оборудования | B4: Средняя | C4: Высокая | D4: Резерв 5–10%, сервис-партнёр в ЕС
A5: Слабая документация OEM | B5: Высокая | C5: Высокая | D5: Аудит соответствия до отгрузки
A6: Зависимость от китайского cloud | B6: Средняя | C6: Высокая | D6: Локальный API, cloud в ЕС, право экспорта данных
A7: Фрагментация интеграций PMS | B7: Высокая | C7: Высокая | D7: Начать с 2–3 PMS
A8: Высокая FDE-нагрузка | B8: Высокая | C8: Средняя | D8: Стандартные коннекторы и SOP
A9: Сезонность Лигурии | B9: Высокая | C9: Высокая | D9: Годовой SaaS, монтаж вне сезона
A10: Нехватка оборотного капитала | B10: Средняя | C10: Высокая | D10: Депозит отеля до заказа hardware
A11: Инцидент GDPR | B11: Низкая | C11: Очень высокая | D11: Минимизация, шифрование, DPA, логирование
A12: Санкции по табаку/vape | B12: Средняя | C12: Очень высокая | D12: Только модель с лицензированным оператором
A13: Экономика роботов не сходится для SMB | B13: Высокая | C13: Средняя | D13: Robot-agnostic ПО; без ранней закупки

Sheet Долговечность
A1: Тренд | B1: Горизонт (лет, оценка) | C1: Оценка долговечности | D1: Инвестиционный вывод
A2: Agentic operations | B2: 7-10 | C2: Очень высокий | D2: Основная software-платформа
A3: Слой идентификации/контекста | B3: 7-10 | C3: Очень высокий | D3: Ключевой архитектурный актив
A4: Многоязычный сервис гостей | B4: 7-10 | C4: Очень высокий (сам по себе не moat) | D4: Базовая функция
A5: Energy IoT | B5: 8-12 | C5: Очень высокий | D5: Самый долговечный hardware-кейс
A6: Smart access | B6: 8-12 | C6: Очень высокий | D6: Зрелая инфраструктура
A7: PMS-нейтральная оркестрация | B7: 5-10 | C7: Высокий | D7: Снижает зависимость от одного PMS
A8: Smart vending / micro-market | B8: 5-8 | C8: Высокий | D8: Стабильный слой физической торговли
A9: Rental-локеры | B9: 5-8 | C9: Высокий | D9: Подходит отелям с малым штатом
A10: Киоски check-in | B10: 4-7 | C10: Средне-высокий | D10: Часть функций уйдёт на телефон
A11: Голосовые ассистенты в номере | B11: 3-6 | C11: Средний | D11: Нужны приватность и доказанное использование
A12: QR-консьерж | B12: 2-4 | C12: Средний | D12: Быстро коммодитизируется
... A15: Vape-vending | B15: 2-5 | C15: Низко-средний | D15: Регуляторный риск выше стратегической ценности

Sheet Примечания
A1: Примечания и ограничения
A2: Финансовые входные данные — плановые допущения (синие ячейки), а не котировки. Landed-стоимость, цены, attach rate и постоянные расходы нужно заменить реальными данными поставщиков/отелей.
A3: Суммы в EUR без НДС; НДС по срокам, перенос убытков, амортизация и стоимость финансирования не моделируются. Landed-стоимость hardware списывается при установке (консервативно).
A4: Рыночные факты из чата (объёмы Лигурии, заявления вендоров, даты регуляции) получены на прежних шагах исследования и в этой сборке не перепроверялись. Перед внешней передачей сверить с первоисточниками (ISTAT/Regione Liguria, ADM, EUR-Lex, Polizia di Stato).
A5: Лист лицензий — ориентировочный чек-лист, не юридическая консультация; подтвердить у итальянского юриста.
A6: Горизонты долговечности трендов — экспертная оценка, не прогноз из источника данных.
A7: Регулируемый vending по умолчанию 0% attach (только модель fee лицензированного партнёра).
